[
    {
        "Set Name": "Base Set",
        "Adj. EV": 0.08320841762405613,
        "Pack Value": 446.71,
        "EV": 37.17003223684211,
        "Last Updated": "2025-07-11 00:55:52",
        "SetNumber": 100
    },
    {
        "Set Name": "Jungle",
        "Adj. EV": 0.09796080227568583,
        "Pack Value": 207.41,
        "EV": 20.31805,
        "Last Updated": "2025-07-11 00:55:52",
        "SetNumber": 101
    },
    {
        "Set Name": "Fossil",
        "Adj. EV": 0.10081591350152484,
        "Pack Value": 216.42,
        "EV": 21.818580000000004,
        "Last Updated": "2025-07-11 00:55:52",
        "SetNumber": 102
    },
    {
        "Set Name": "Base Set 2",
        "Adj. EV": 0.09780561399250207,
        "Pack Value": 247.18,
        "EV": 24.175591666666662,
        "Last Updated": "2025-07-11 00:55:52",
        "SetNumber": 103
    },
    {
        "Set Name": "Team Rocket",
        "Adj. EV": 0.15161794022347183,
        "Pack Value": 254.9,
        "EV": 38.64741296296297,
        "Last Updated": "2025-07-11 00:55:52",
        "SetNumber": 104
    },
    {
        "Set Name": "Gym Heroes",
        "Adj. EV": 0.13098709159983116,
        "Pack Value": 257.5,
        "EV": 33.72917608695652,
        "Last Updated": "2025-07-11 00:55:52",
        "SetNumber": 105
    },
    {
        "Set Name": "Gym Challenge",
        "Adj. EV": 0.21067062983712428,
        "Pack Value": 241.99,
        "EV": 50.98018571428571,
        "Last Updated": "2025-07-11 00:55:52",
        "SetNumber": 106
    },
    {
        "Set Name": "Neo Genesis",
        "Adj. EV": 0.06571906412666281,
        "Pack Value": 520.0,
        "EV": 34.17391334586466,
        "Last Updated": "2025-07-11 00:55:52",
        "SetNumber": 107
    },
    {
        "Set Name": "Neo Discovery",
        "Adj. EV": 0.0931161286963652,
        "Pack Value": 370.47,
        "EV": 34.49673219814242,
        "Last Updated": "2025-07-11 00:55:52",
        "SetNumber": 108
    },
    {
        "Set Name": "Neo Revelation",
        "Adj. EV": 0.165408686704036,
        "Pack Value": 398.33,
        "EV": 65.88724217481865,
        "Last Updated": "2025-07-11 00:55:52",
        "SetNumber": 109
    },
    {
        "Set Name": "Neo Destiny",
        "Adj. EV": 0.1641427050014088,
        "Pack Value": 599.99,
        "EV": 98.48398157379526,
        "Last Updated": "2025-07-11 00:55:52",
        "SetNumber": 110
    },
    {
        "Set Name": "Legendary Collection",
        "Adj. EV": 0.08717963475883386,
        "Pack Value": 1610.0,
        "EV": 140.3592119617225,
        "Last Updated": "2025-07-11 00:55:52",
        "SetNumber": 200
    },
    {
        "Set Name": "Expedition",
        "Adj. EV": 0.11245487584461882,
        "Pack Value": 1087.5,
        "EV": 122.29467748102296,
        "Last Updated": "2025-07-11 00:55:52",
        "SetNumber": 201
    },
    {
        "Set Name": "Aquapolis",
        "Adj. EV": 0.15126189561849887,
        "Pack Value": 901.99,
        "EV": 136.4367172289298,
        "Last Updated": "2025-07-11 00:55:52",
        "SetNumber": 202
    },
    {
        "Set Name": "Skyridge",
        "Adj. EV": 0.13575665946693413,
        "Pack Value": 1799.99,
        "EV": 244.36062947388677,
        "Last Updated": "2025-07-11 00:55:52",
        "SetNumber": 203
    },
    {
        "Set Name": "Ruby and Sapphire",
        "Adj. EV": 0.07201791173102906,
        "Pack Value": 350.0,
        "EV": 25.206269105860173,
        "Last Updated": "2025-07-11 00:55:52",
        "SetNumber": 300
    },
    {
        "Set Name": "Sandstorm",
        "Adj. EV": 0.06834166922756105,
        "Pack Value": 499.95,
        "EV": 34.16741753031914,
        "Last Updated": "2025-07-11 00:55:52",
        "SetNumber": 301
    },
    {
        "Set Name": "Dragon",
        "Adj. EV": 0.04506542469737192,
        "Pack Value": 827.49,
        "EV": 37.29118828282829,
        "Last Updated": "2025-07-11 00:55:52",
        "SetNumber": 302
    },
    {
        "Set Name": "Team Magma vs Team Aqua",
        "Adj. EV": 0.11967683072520167,
        "Pack Value": 399.0,
        "EV": 47.75105545935547,
        "Last Updated": "2025-07-11 00:55:52",
        "SetNumber": 303
    },
    {
        "Set Name": "Hidden Legends",
        "Adj. EV": 0.1311263851617626,
        "Pack Value": 250.0,
        "EV": 32.781596290440646,
        "Last Updated": "2025-07-11 00:55:52",
        "SetNumber": 304
    },
    {
        "Set Name": "FireRed & LeafGreen",
        "Adj. EV": 0.08229030052612647,
        "Pack Value": 622.48,
        "EV": 51.224066271503204,
        "Last Updated": "2025-07-11 00:55:52",
        "SetNumber": 305
    },
    {
        "Set Name": "Emerald",
        "Adj. EV": 0.10010223231123118,
        "Pack Value": 450.0,
        "EV": 45.04600454005403,
        "Last Updated": "2025-07-11 00:55:52",
        "SetNumber": 306
    },
    {
        "Set Name": "Team Rocket Returns",
        "Adj. EV": 0.08158890469878452,
        "Pack Value": 1495.0,
        "EV": 121.97541252468287,
        "Last Updated": "2025-07-11 00:55:52",
        "SetNumber": 400
    },
    {
        "Set Name": "Deoxys",
        "Adj. EV": 0.042610826627928325,
        "Pack Value": 1099.0,
        "EV": 46.82929846409323,
        "Last Updated": "2025-07-11 00:55:52",
        "SetNumber": 401
    },
    {
        "Set Name": "Unseen Forces",
        "Adj. EV": 0.0787875486521629,
        "Pack Value": 699.99,
        "EV": 55.15049618102751,
        "Last Updated": "2025-07-11 00:55:52",
        "SetNumber": 402
    },
    {
        "Set Name": "Delta Species",
        "Adj. EV": 0.13037670879617547,
        "Pack Value": 748.69,
        "EV": 97.61173810860862,
        "Last Updated": "2025-07-11 00:55:52",
        "SetNumber": 403
    },
    {
        "Set Name": "Legend Maker",
        "Adj. EV": 0.1149758353919184,
        "Pack Value": 324.98,
        "EV": 37.36484698566564,
        "Last Updated": "2025-07-11 00:55:52",
        "SetNumber": 404
    },
    {
        "Set Name": "Holon Phantoms",
        "Adj. EV": 0.11674085030859563,
        "Pack Value": 566.65,
        "EV": 66.15120282736571,
        "Last Updated": "2025-07-11 00:55:52",
        "SetNumber": 405
    },
    {
        "Set Name": "Crystal Guardians",
        "Adj. EV": 0.10369107858743878,
        "Pack Value": 459.74,
        "EV": 47.670936469789105,
        "Last Updated": "2025-07-11 00:55:52",
        "SetNumber": 406
    },
    {
        "Set Name": "Dragon Frontiers",
        "Adj. EV": 0.09405924688040376,
        "Pack Value": 551.99,
        "EV": 51.91976368551408,
        "Last Updated": "2025-07-11 00:55:52",
        "SetNumber": 407
    },
    {
        "Set Name": "Power Keepers",
        "Adj. EV": 0.03769313263520684,
        "Pack Value": 850.0,
        "EV": 32.039162739925814,
        "Last Updated": "2025-07-11 00:55:52",
        "SetNumber": 408
    },
    {
        "Set Name": "Diamond and Pearl",
        "Adj. EV": 0.13148259252457498,
        "Pack Value": 143.0,
        "EV": 18.80201073101422,
        "Last Updated": "2025-07-11 00:55:52",
        "SetNumber": 500
    },
    {
        "Set Name": "Mysterious Treasures",
        "Adj. EV": 0.10717374829410521,
        "Pack Value": 127.96,
        "EV": 13.713952831713701,
        "Last Updated": "2025-07-11 00:55:52",
        "SetNumber": 501
    },
    {
        "Set Name": "Secret Wonders",
        "Adj. EV": 0.08414000044679713,
        "Pack Value": 249.99,
        "EV": 21.034158711694815,
        "Last Updated": "2025-07-11 00:55:52",
        "SetNumber": 502
    },
    {
        "Set Name": "Great Encounters",
        "Adj. EV": 0.0901894834656466,
        "Pack Value": 189.99,
        "EV": 17.1350999636382,
        "Last Updated": "2025-07-11 00:55:52",
        "SetNumber": 503
    },
    {
        "Set Name": "Majestic Dawn",
        "Adj. EV": 0.0704475611111111,
        "Pack Value": 450.0,
        "EV": 31.701402499999993,
        "Last Updated": "2025-07-11 00:55:52",
        "SetNumber": 504
    },
    {
        "Set Name": "Legends Awakened",
        "Adj. EV": 0.09104603972000157,
        "Pack Value": 267.97,
        "EV": 24.397607263768823,
        "Last Updated": "2025-07-11 00:55:52",
        "SetNumber": 505
    },
    {
        "Set Name": "Stormfront",
        "Adj. EV": 0.13068230780641732,
        "Pack Value": 180.0,
        "EV": 23.522815405155118,
        "Last Updated": "2025-07-11 00:55:52",
        "SetNumber": 506
    },
    {
        "Set Name": "Platinum",
        "Adj. EV": 0.1437123531728733,
        "Pack Value": 136.99,
        "EV": 19.68715526115191,
        "Last Updated": "2025-07-11 00:55:52",
        "SetNumber": 507
    },
    {
        "Set Name": "Rising Rivals",
        "Adj. EV": 0.13972134416744147,
        "Pack Value": 199.99,
        "EV": 27.942871620046624,
        "Last Updated": "2025-07-11 00:55:52",
        "SetNumber": 508
    },
    {
        "Set Name": "Supreme Victors",
        "Adj. EV": 0.07613514748880172,
        "Pack Value": 399.99,
        "EV": 30.4532976440458,
        "Last Updated": "2025-07-11 00:55:52",
        "SetNumber": 509
    },
    {
        "Set Name": "Arceus",
        "Adj. EV": 0.1405654400371457,
        "Pack Value": 172.59,
        "EV": 24.260189296010974,
        "Last Updated": "2025-07-11 00:55:52",
        "SetNumber": 510
    },
    {
        "Set Name": "HeartGold SoulSilver",
        "Adj. EV": 0.19841259778662632,
        "Pack Value": 287.5,
        "EV": 57.04362186365506,
        "Last Updated": "2025-07-11 00:55:52",
        "SetNumber": 600
    },
    {
        "Set Name": "Unleashed",
        "Adj. EV": 0.13082140018854305,
        "Pack Value": 174.99,
        "EV": 22.892436818993147,
        "Last Updated": "2025-07-11 00:55:52",
        "SetNumber": 601
    },
    {
        "Set Name": "Undaunted",
        "Adj. EV": 0.17344038406484524,
        "Pack Value": 201.51,
        "EV": 34.949971792906965,
        "Last Updated": "2025-07-11 00:55:52",
        "SetNumber": 602
    },
    {
        "Set Name": "Triumphant",
        "Adj. EV": 0.17385996749290458,
        "Pack Value": 130.0,
        "EV": 22.601795774077594,
        "Last Updated": "2025-07-11 00:55:52",
        "SetNumber": 603
    },
    {
        "Set Name": "Call of Legends",
        "Adj. EV": 0.15828498259469567,
        "Pack Value": 355.0,
        "EV": 56.19116882111697,
        "Last Updated": "2025-07-11 00:55:52",
        "SetNumber": 604
    },
    {
        "Set Name": "Black and White",
        "Adj. EV": 0.16109223091454025,
        "Pack Value": 79.07,
        "EV": 12.737562698412697,
        "Last Updated": "2025-07-11 00:55:52",
        "SetNumber": 700
    },
    {
        "Set Name": "Emerging Powers",
        "Adj. EV": 0.0764039777783254,
        "Pack Value": 68.75,
        "EV": 5.252773472259872,
        "Last Updated": "2025-07-11 00:55:52",
        "SetNumber": 701
    },
    {
        "Set Name": "Noble Victories",
        "Adj. EV": 0.1274155363328799,
        "Pack Value": 109.18,
        "EV": 13.911228256823826,
        "Last Updated": "2025-07-11 00:55:52",
        "SetNumber": 702
    },
    {
        "Set Name": "Next Destinies",
        "Adj. EV": 0.12286769467810245,
        "Pack Value": 84.91,
        "EV": 10.432695955117678,
        "Last Updated": "2025-07-11 00:55:52",
        "SetNumber": 703
    },
    {
        "Set Name": "Dark Explorers",
        "Adj. EV": 0.07115260279697559,
        "Pack Value": 350.0,
        "EV": 24.90341097894146,
        "Last Updated": "2025-07-11 00:55:52",
        "SetNumber": 704
    },
    {
        "Set Name": "Dragons Exalted",
        "Adj. EV": 0.10486762210825314,
        "Pack Value": 145.16,
        "EV": 15.222584025234026,
        "Last Updated": "2025-07-11 00:55:52",
        "SetNumber": 705
    },
    {
        "Set Name": "Boundaries Crossed",
        "Adj. EV": 0.11470838372272758,
        "Pack Value": 126.61,
        "EV": 14.52322846313454,
        "Last Updated": "2025-07-11 00:55:52",
        "SetNumber": 706
    },
    {
        "Set Name": "Plasma Storm",
        "Adj. EV": 0.07142650059110728,
        "Pack Value": 253.31,
        "EV": 18.093046864733385,
        "Last Updated": "2025-07-11 00:55:52",
        "SetNumber": 707
    },
    {
        "Set Name": "Plasma Freeze",
        "Adj. EV": 0.13091183200595377,
        "Pack Value": 142.9,
        "EV": 18.707300793650795,
        "Last Updated": "2025-07-11 00:55:52",
        "SetNumber": 708
    },
    {
        "Set Name": "Plasma Blast",
        "Adj. EV": 0.12565301706232426,
        "Pack Value": 82.52,
        "EV": 10.368886967982997,
        "Last Updated": "2025-07-11 00:55:52",
        "SetNumber": 709
    },
    {
        "Set Name": "Legendary Treasures",
        "Adj. EV": 0.2635636083901001,
        "Pack Value": 134.08,
        "EV": 35.338608612944626,
        "Last Updated": "2025-07-11 00:55:52",
        "SetNumber": 710
    },
    {
        "Set Name": "XY Base Set",
        "Adj. EV": 0.143463656234341,
        "Pack Value": 48.05,
        "EV": 6.893428682060086,
        "Last Updated": "2025-07-11 00:55:52",
        "SetNumber": 800
    },
    {
        "Set Name": "XY - Flashfire",
        "Adj. EV": 0.15041887612355484,
        "Pack Value": 81.36,
        "EV": 12.238079761412422,
        "Last Updated": "2025-07-11 00:55:52",
        "SetNumber": 801
    },
    {
        "Set Name": "XY - Furious Fists",
        "Adj. EV": 0.22272790256397537,
        "Pack Value": 42.96,
        "EV": 9.568390694148382,
        "Last Updated": "2025-07-11 00:55:52",
        "SetNumber": 802
    },
    {
        "Set Name": "XY - Phantom Forces",
        "Adj. EV": 0.15887506823132375,
        "Pack Value": 87.9,
        "EV": 13.965118497533357,
        "Last Updated": "2025-07-11 00:55:52",
        "SetNumber": 803
    },
    {
        "Set Name": "XY - Primal Clash",
        "Adj. EV": 0.2289652692074088,
        "Pack Value": 37.53,
        "EV": 8.593066553354053,
        "Last Updated": "2025-07-11 00:55:52",
        "SetNumber": 804
    },
    {
        "Set Name": "XY - Roaring Skies",
        "Adj. EV": 0.23582032808585865,
        "Pack Value": 37.72,
        "EV": 8.895142775398588,
        "Last Updated": "2025-07-11 00:55:52",
        "SetNumber": 805
    },
    {
        "Set Name": "XY - Ancient Origins",
        "Adj. EV": 0.2921036694269353,
        "Pack Value": 48.47,
        "EV": 14.158264857123552,
        "Last Updated": "2025-07-11 00:55:52",
        "SetNumber": 806
    },
    {
        "Set Name": "XY - BREAKthrough",
        "Adj. EV": 0.4791461597800174,
        "Pack Value": 26.39,
        "EV": 12.64466715659466,
        "Last Updated": "2025-07-11 00:55:52",
        "SetNumber": 807
    },
    {
        "Set Name": "XY - BREAKpoint",
        "Adj. EV": 0.43299176106777904,
        "Pack Value": 23.25,
        "EV": 10.067058444825863,
        "Last Updated": "2025-07-11 00:55:52",
        "SetNumber": 808
    },
    {
        "Set Name": "XY - Fates Collide",
        "Adj. EV": 0.32572900434017504,
        "Pack Value": 25.53,
        "EV": 8.315861480804669,
        "Last Updated": "2025-07-11 00:55:52",
        "SetNumber": 809
    },
    {
        "Set Name": "XY - Steam Siege",
        "Adj. EV": 0.30117949490385815,
        "Pack Value": 17.65,
        "EV": 5.315818085053095,
        "Last Updated": "2025-07-11 00:55:52",
        "SetNumber": 810
    },
    {
        "Set Name": "XY - Evolutions",
        "Adj. EV": 0.26776951594475357,
        "Pack Value": 38.91,
        "EV": 10.41891186541036,
        "Last Updated": "2025-07-11 00:55:52",
        "SetNumber": 811
    },
    {
        "Set Name": "SM Base Set",
        "Adj. EV": 0.22775929765196926,
        "Pack Value": 13.24,
        "EV": 3.015533100912073,
        "Last Updated": "2025-07-11 00:55:52",
        "SetNumber": 900
    },
    {
        "Set Name": "SM - Guardians Rising",
        "Adj. EV": 0.1686335896727302,
        "Pack Value": 19.91,
        "EV": 3.3574947703840583,
        "Last Updated": "2025-07-11 00:55:52",
        "SetNumber": 901
    },
    {
        "Set Name": "SM - Burning Shadows",
        "Adj. EV": 0.2145583812504939,
        "Pack Value": 17.11,
        "EV": 3.6710939031959504,
        "Last Updated": "2025-07-11 00:55:52",
        "SetNumber": 902
    },
    {
        "Set Name": "SM - Crimson Invasion",
        "Adj. EV": 0.28548872599901287,
        "Pack Value": 10.88,
        "EV": 3.1061173388692604,
        "Last Updated": "2025-07-11 00:55:52",
        "SetNumber": 903
    },
    {
        "Set Name": "SM - Ultra Prism",
        "Adj. EV": 0.2475587013370217,
        "Pack Value": 31.58,
        "EV": 7.817903788223145,
        "Last Updated": "2025-07-11 00:55:52",
        "SetNumber": 904
    },
    {
        "Set Name": "SM - Forbidden Light",
        "Adj. EV": 0.27704747774637395,
        "Pack Value": 22.83,
        "EV": 6.324993916949717,
        "Last Updated": "2025-07-11 00:55:52",
        "SetNumber": 905
    },
    {
        "Set Name": "SM - Celestial Storm",
        "Adj. EV": 0.1536029893660016,
        "Pack Value": 37.71,
        "EV": 5.792368728991921,
        "Last Updated": "2025-07-11 00:55:52",
        "SetNumber": 906
    },
    {
        "Set Name": "SM - Lost Thunder",
        "Adj. EV": 0.24469248896018386,
        "Pack Value": 27.51,
        "EV": 6.731490371294658,
        "Last Updated": "2025-07-11 00:55:52",
        "SetNumber": 907
    },
    {
        "Set Name": "SM - Team Up",
        "Adj. EV": 0.10956344062220681,
        "Pack Value": 163.45,
        "EV": 17.908144369699702,
        "Last Updated": "2025-07-11 00:55:52",
        "SetNumber": 908
    },
    {
        "Set Name": "SM - Unbroken Bonds",
        "Adj. EV": 0.20189820293095262,
        "Pack Value": 44.4,
        "EV": 8.964280210134296,
        "Last Updated": "2025-07-11 00:55:52",
        "SetNumber": 909
    },
    {
        "Set Name": "SM - Unified Minds",
        "Adj. EV": 0.24982847802704425,
        "Pack Value": 39.34,
        "EV": 9.828252325583922,
        "Last Updated": "2025-07-11 00:55:52",
        "SetNumber": 910
    },
    {
        "Set Name": "SM - Cosmic Eclipse",
        "Adj. EV": 0.2725964640371508,
        "Pack Value": 47.14,
        "EV": 12.85019731471129,
        "Last Updated": "2025-07-11 00:55:52",
        "SetNumber": 911
    },
    {
        "Set Name": "SWSH01: Sword & Shield Base Set",
        "Adj. EV": 0.3085740695992804,
        "Pack Value": 7.39,
        "EV": 2.280362374338682,
        "Last Updated": "2025-07-11 00:55:52",
        "SetNumber": 1000
    },
    {
        "Set Name": "SWSH02: Rebel Clash",
        "Adj. EV": 0.3199552598718523,
        "Pack Value": 7.19,
        "EV": 2.300478318478618,
        "Last Updated": "2025-07-11 00:55:52",
        "SetNumber": 1001
    },
    {
        "Set Name": "SWSH03: Darkness Ablaze",
        "Adj. EV": 0.2824240427920389,
        "Pack Value": 5.88,
        "EV": 1.6606533716171887,
        "Last Updated": "2025-07-11 00:55:52",
        "SetNumber": 1002
    },
    {
        "Set Name": "SWSH04: Vivid Voltage",
        "Adj. EV": 0.311743747184039,
        "Pack Value": 6.71,
        "EV": 2.0918005436049016,
        "Last Updated": "2025-07-11 00:55:52",
        "SetNumber": 1003
    },
    {
        "Set Name": "SWSH05: Battle Styles",
        "Adj. EV": 0.28415250751569027,
        "Pack Value": 6.27,
        "EV": 1.7816362221233777,
        "Last Updated": "2025-07-11 00:55:52",
        "SetNumber": 1004
    },
    {
        "Set Name": "SWSH06: Chilling Reign",
        "Adj. EV": 0.26983791437315563,
        "Pack Value": 7.97,
        "EV": 2.15060817755405,
        "Last Updated": "2025-07-11 00:55:52",
        "SetNumber": 1005
    },
    {
        "Set Name": "SWSH07: Evolving Skies",
        "Adj. EV": 0.23449951343718525,
        "Pack Value": 24.6,
        "EV": 5.768688030554758,
        "Last Updated": "2025-07-11 00:55:52",
        "SetNumber": 1006
    },
    {
        "Set Name": "SWSH08: Fusion Strike",
        "Adj. EV": 0.20256505175331158,
        "Pack Value": 12.63,
        "EV": 2.5583966036443253,
        "Last Updated": "2025-07-11 00:55:52",
        "SetNumber": 1007
    },
    {
        "Set Name": "SWSH09: Brilliant Stars",
        "Adj. EV": 0.5408705588982472,
        "Pack Value": 8.07,
        "EV": 4.364825410308855,
        "Last Updated": "2025-07-11 00:55:52",
        "SetNumber": 1100
    },
    {
        "Set Name": "SWSH10: Astral Radiance",
        "Adj. EV": 0.4392545311089,
        "Pack Value": 6.58,
        "EV": 2.890294814696562,
        "Last Updated": "2025-07-11 00:55:52",
        "SetNumber": 1101
    },
    {
        "Set Name": "SWSH11: Lost Origin",
        "Adj. EV": 0.34618670259000783,
        "Pack Value": 9.61,
        "EV": 3.326854211889975,
        "Last Updated": "2025-07-11 00:55:52",
        "SetNumber": 1102
    },
    {
        "Set Name": "SWSH12: Silver Tempest",
        "Adj. EV": 0.40476288251374376,
        "Pack Value": 6.65,
        "EV": 2.691673168716396,
        "Last Updated": "2025-07-11 00:55:52",
        "SetNumber": 1103
    },
    {
        "Set Name": "SV01: Scarlet & Violet Base Set",
        "Adj. EV": 0.4645767968654793,
        "Pack Value": 5.83,
        "EV": 2.7084827257257444,
        "Last Updated": "2025-07-11 00:55:52",
        "SetNumber": 1200
    },
    {
        "Set Name": "SV02: Paldea Evolved",
        "Adj. EV": 0.4084063364120918,
        "Pack Value": 8.17,
        "EV": 3.33667976848679,
        "Last Updated": "2025-07-11 00:55:52",
        "SetNumber": 1201
    },
    {
        "Set Name": "SV03: Obsidian Flames",
        "Adj. EV": 0.3650413945602558,
        "Pack Value": 6.8,
        "EV": 2.4822814830097393,
        "Last Updated": "2025-07-11 00:55:52",
        "SetNumber": 1202
    },
    {
        "Set Name": "SV04: Paradox Rift",
        "Adj. EV": 0.44604708254195535,
        "Pack Value": 5.66,
        "EV": 2.5246264871874673,
        "Last Updated": "2025-07-11 00:55:52",
        "SetNumber": 1203
    },
    {
        "Set Name": "SV05: Temporal Forces",
        "Adj. EV": 0.39026129416416183,
        "Pack Value": 6.48,
        "EV": 2.528893186183769,
        "Last Updated": "2025-07-11 00:55:52",
        "SetNumber": 1204
    },
    {
        "Set Name": "SV06: Twilight Masquerade",
        "Adj. EV": 0.44712580898418025,
        "Pack Value": 6.39,
        "EV": 2.857133919408912,
        "Last Updated": "2025-07-11 00:55:52",
        "SetNumber": 1205
    },
    {
        "Set Name": "SV07: Stellar Crown",
        "Adj. EV": 0.3821945095027176,
        "Pack Value": 6.36,
        "EV": 2.4307570804372842,
        "Last Updated": "2025-07-11 00:55:52",
        "SetNumber": 1206
    },
    {
        "Set Name": "SV08: Surging Sparks",
        "Adj. EV": 0.3773123495597698,
        "Pack Value": 7.09,
        "EV": 2.6751445583787676,
        "Last Updated": "2025-07-11 00:55:52",
        "SetNumber": 1207
    },
    {
        "Set Name": "Dragon Vault",
        "Adj. EV": 0.15971957420842087,
        "Pack Value": 147.49,
        "EV": 23.557039999999997,
        "Last Updated": "2025-07-11 00:55:52",
        "SetNumber": 705.5
    },
    {
        "Set Name": "Double Crisis",
        "Adj. EV": 0.3205363899958036,
        "Pack Value": 169.33,
        "EV": 54.276426917989426,
        "Last Updated": "2025-07-11 00:55:52",
        "SetNumber": 804.5
    },
    {
        "Set Name": "Shining Legends",
        "Adj. EV": 0.18871595353756598,
        "Pack Value": 51.71,
        "EV": 9.758501957427537,
        "Last Updated": "2025-07-11 00:55:52",
        "SetNumber": 902.5
    },
    {
        "Set Name": "Dragon Majesty",
        "Adj. EV": 0.20437079840288327,
        "Pack Value": 45.99,
        "EV": 9.399013018548603,
        "Last Updated": "2025-07-11 00:55:52",
        "SetNumber": 906.5
    },
    {
        "Set Name": "Champions Path",
        "Adj. EV": 0.24533515377234472,
        "Pack Value": 12.72,
        "EV": 3.120663155984225,
        "Last Updated": "2025-07-11 00:55:52",
        "SetNumber": 1002.5
    },
    {
        "Set Name": "Pokemon Go",
        "Adj. EV": 0.5089994861550832,
        "Pack Value": 6.03,
        "EV": 3.0692669015151517,
        "Last Updated": "2025-07-11 00:55:52",
        "SetNumber": 1101.5
    },
    {
        "Set Name": "Pokemon 151",
        "Adj. EV": 0.5570530091269952,
        "Pack Value": 10.75,
        "EV": 5.988319848115198,
        "Last Updated": "2025-07-11 00:55:52",
        "SetNumber": 1202.5
    },
    {
        "Set Name": "Paldean Fates",
        "Adj. EV": 0.3134496428749056,
        "Pack Value": 12.2,
        "EV": 3.824085643073848,
        "Last Updated": "2025-07-11 00:55:52",
        "SetNumber": 1203.5
    },
    {
        "Set Name": "Shrouded Fable",
        "Adj. EV": 0.5767150494146112,
        "Pack Value": 7.37,
        "EV": 4.250389914185685,
        "Last Updated": "2025-07-11 00:55:52",
        "SetNumber": 1205.5
    },
    {
        "Set Name": "Hidden Fates",
        "Adj. EV": 0.31798517806749943,
        "Pack Value": 35.67,
        "EV": 11.342531301667705,
        "Last Updated": "2025-07-11 00:55:52",
        "SetNumber": 910.5
    },
    {
        "Set Name": "Shining Fates",
        "Adj. EV": 0.2620898334457407,
        "Pack Value": 9.38,
        "EV": 2.458402637721048,
        "Last Updated": "2025-07-11 00:55:52",
        "SetNumber": 1003.5
    },
    {
        "Set Name": "Generations",
        "Adj. EV": 0.22927181673690272,
        "Pack Value": 166.06,
        "EV": 38.072877887330066,
        "Last Updated": "2025-07-11 00:55:52",
        "SetNumber": 808.5
    },
    {
        "Set Name": "Crown Zenith",
        "Adj. EV": 0.4848419828125167,
        "Pack Value": 10.47,
        "EV": 5.0762955600470505,
        "Last Updated": "2025-07-11 00:55:52",
        "SetNumber": 1103.5
    },
    {
        "Set Name": "Celebrations",
        "Adj. EV": 0.41522567857574727,
        "Pack Value": 13.45,
        "EV": 5.584785376843801,
        "Last Updated": "2025-07-11 00:55:52",
        "SetNumber": 1006.5
    },
    {
        "Set Name": "Prismatic Evolutions",
        "Adj. EV": 0.47499306702016963,
        "Pack Value": 10.45,
        "EV": 4.963677550360773,
        "Last Updated": "2025-07-11 00:55:52",
        "SetNumber": 1207.5
    }
]