[
    {
        "Set Name": "Base Set",
        "Adj. EV": 0.08070579403097147,
        "Pack Value": 465.42,
        "EV": 37.56209065789474,
        "Last Updated": "2025-09-03 00:46:22",
        "SetNumber": 100
    },
    {
        "Set Name": "Jungle",
        "Adj. EV": 0.09656728229185643,
        "Pack Value": 219.56,
        "EV": 21.202312499999998,
        "Last Updated": "2025-09-03 00:46:22",
        "SetNumber": 101
    },
    {
        "Set Name": "Fossil",
        "Adj. EV": 0.10029822379331413,
        "Pack Value": 229.14,
        "EV": 22.982335,
        "Last Updated": "2025-09-03 00:46:22",
        "SetNumber": 102
    },
    {
        "Set Name": "Base Set 2",
        "Adj. EV": 0.09697336948842863,
        "Pack Value": 246.03,
        "EV": 23.858358095238096,
        "Last Updated": "2025-09-03 00:46:22",
        "SetNumber": 103
    },
    {
        "Set Name": "Team Rocket",
        "Adj. EV": 0.15547584910271864,
        "Pack Value": 257.97,
        "EV": 40.10810479302833,
        "Last Updated": "2025-09-03 00:46:22",
        "SetNumber": 104
    },
    {
        "Set Name": "Gym Heroes",
        "Adj. EV": 0.13596548695468952,
        "Pack Value": 262.16,
        "EV": 35.64471206004141,
        "Last Updated": "2025-09-03 00:46:22",
        "SetNumber": 105
    },
    {
        "Set Name": "Gym Challenge",
        "Adj. EV": 0.22653249806042217,
        "Pack Value": 246.74,
        "EV": 55.89462857142857,
        "Last Updated": "2025-09-03 00:46:22",
        "SetNumber": 106
    },
    {
        "Set Name": "Neo Genesis",
        "Adj. EV": 0.06191954271023822,
        "Pack Value": 560.25,
        "EV": 34.690423803410965,
        "Last Updated": "2025-09-03 00:46:22",
        "SetNumber": 107
    },
    {
        "Set Name": "Neo Discovery",
        "Adj. EV": 0.10241049999397836,
        "Pack Value": 357.33,
        "EV": 36.594343962848285,
        "Last Updated": "2025-09-03 00:46:22",
        "SetNumber": 108
    },
    {
        "Set Name": "Neo Revelation",
        "Adj. EV": 0.16142725893513224,
        "Pack Value": 422.5,
        "EV": 68.20301690009337,
        "Last Updated": "2025-09-03 00:46:22",
        "SetNumber": 109
    },
    {
        "Set Name": "Neo Destiny",
        "Adj. EV": 0.2058979070930672,
        "Pack Value": 799.0,
        "EV": 164.5124277673607,
        "Last Updated": "2025-09-03 00:46:22",
        "SetNumber": 110
    },
    {
        "Set Name": "Legendary Collection",
        "Adj. EV": 0.09912918214508601,
        "Pack Value": 1610.0,
        "EV": 159.59798325358847,
        "Last Updated": "2025-09-03 00:46:22",
        "SetNumber": 200
    },
    {
        "Set Name": "Expedition",
        "Adj. EV": 0.12299704587488133,
        "Pack Value": 1100.0,
        "EV": 135.29675046236946,
        "Last Updated": "2025-09-03 00:46:22",
        "SetNumber": 201
    },
    {
        "Set Name": "Aquapolis",
        "Adj. EV": 0.13998472766817502,
        "Pack Value": 1050.99,
        "EV": 147.12254893197527,
        "Last Updated": "2025-09-03 00:46:22",
        "SetNumber": 202
    },
    {
        "Set Name": "Skyridge",
        "Adj. EV": 0.1503778633222415,
        "Pack Value": 1774.495,
        "EV": 266.84476657600095,
        "Last Updated": "2025-09-03 00:46:22",
        "SetNumber": 203
    },
    {
        "Set Name": "Ruby and Sapphire",
        "Adj. EV": 0.4584046133514624,
        "Pack Value": 59.99,
        "EV": 27.49969275495423,
        "Last Updated": "2025-09-03 00:46:22",
        "SetNumber": 300
    },
    {
        "Set Name": "Sandstorm",
        "Adj. EV": 0.07362672650774042,
        "Pack Value": 499.95,
        "EV": 36.80968191754482,
        "Last Updated": "2025-09-03 00:46:22",
        "SetNumber": 301
    },
    {
        "Set Name": "Dragon",
        "Adj. EV": 0.0496314867148739,
        "Pack Value": 897.5,
        "EV": 44.544259326599324,
        "Last Updated": "2025-09-03 00:46:22",
        "SetNumber": 302
    },
    {
        "Set Name": "Team Magma vs Team Aqua",
        "Adj. EV": 0.13417999353856022,
        "Pack Value": 375.0,
        "EV": 50.31749757696008,
        "Last Updated": "2025-09-03 00:46:22",
        "SetNumber": 303
    },
    {
        "Set Name": "Hidden Legends",
        "Adj. EV": 0.1026601726498944,
        "Pack Value": 350.0,
        "EV": 35.93106042746304,
        "Last Updated": "2025-09-03 00:46:22",
        "SetNumber": 304
    },
    {
        "Set Name": "FireRed & LeafGreen",
        "Adj. EV": 0.08850762135539617,
        "Pack Value": 622.48,
        "EV": 55.09422414130701,
        "Last Updated": "2025-09-03 00:46:22",
        "SetNumber": 305
    },
    {
        "Set Name": "Emerald",
        "Adj. EV": 0.10955374439966575,
        "Pack Value": 424.5,
        "EV": 46.50556449765811,
        "Last Updated": "2025-09-03 00:46:22",
        "SetNumber": 306
    },
    {
        "Set Name": "Team Rocket Returns",
        "Adj. EV": 0.06288963405590171,
        "Pack Value": 1999.99,
        "EV": 125.77863921546287,
        "Last Updated": "2025-09-03 00:46:22",
        "SetNumber": 400
    },
    {
        "Set Name": "Deoxys",
        "Adj. EV": 0.0287364570552959,
        "Pack Value": 1599.99,
        "EV": 45.97804392390289,
        "Last Updated": "2025-09-03 00:46:22",
        "SetNumber": 401
    },
    {
        "Set Name": "Unseen Forces",
        "Adj. EV": 0.08822337871782925,
        "Pack Value": 699.97,
        "EV": 61.75371840111894,
        "Last Updated": "2025-09-03 00:46:22",
        "SetNumber": 402
    },
    {
        "Set Name": "Delta Species",
        "Adj. EV": 0.1488893792413975,
        "Pack Value": 749.975,
        "EV": 111.66331219656709,
        "Last Updated": "2025-09-03 00:46:22",
        "SetNumber": 403
    },
    {
        "Set Name": "Legend Maker",
        "Adj. EV": 0.08652942288384069,
        "Pack Value": 499.99,
        "EV": 43.26384614769151,
        "Last Updated": "2025-09-03 00:46:22",
        "SetNumber": 404
    },
    {
        "Set Name": "Holon Phantoms",
        "Adj. EV": 0.10300230727069654,
        "Pack Value": 699.95,
        "EV": 72.09646497412405,
        "Last Updated": "2025-09-03 00:46:22",
        "SetNumber": 405
    },
    {
        "Set Name": "Crystal Guardians",
        "Adj. EV": 0.09551990800186827,
        "Pack Value": 499.99,
        "EV": 47.75899880185412,
        "Last Updated": "2025-09-03 00:46:22",
        "SetNumber": 406
    },
    {
        "Set Name": "Dragon Frontiers",
        "Adj. EV": 0.06157228221650143,
        "Pack Value": 899.95,
        "EV": 55.411975380740465,
        "Last Updated": "2025-09-03 00:46:22",
        "SetNumber": 407
    },
    {
        "Set Name": "Power Keepers",
        "Adj. EV": 0.0493969416478985,
        "Pack Value": 849.0,
        "EV": 41.938003459065825,
        "Last Updated": "2025-09-03 00:46:22",
        "SetNumber": 408
    },
    {
        "Set Name": "Diamond and Pearl",
        "Adj. EV": 0.1366572755468535,
        "Pack Value": 152.8,
        "EV": 20.881231703559216,
        "Last Updated": "2025-09-03 00:46:22",
        "SetNumber": 500
    },
    {
        "Set Name": "Mysterious Treasures",
        "Adj. EV": 0.10683762177078705,
        "Pack Value": 143.15,
        "EV": 15.293805556488167,
        "Last Updated": "2025-09-03 00:46:22",
        "SetNumber": 501
    },
    {
        "Set Name": "Secret Wonders",
        "Adj. EV": 0.0719343350745391,
        "Pack Value": 312.0,
        "EV": 22.443512543256197,
        "Last Updated": "2025-09-03 00:46:22",
        "SetNumber": 502
    },
    {
        "Set Name": "Great Encounters",
        "Adj. EV": 0.09693272711454783,
        "Pack Value": 189.99,
        "EV": 18.416248824492943,
        "Last Updated": "2025-09-03 00:46:22",
        "SetNumber": 503
    },
    {
        "Set Name": "Majestic Dawn",
        "Adj. EV": 0.07611333253968254,
        "Pack Value": 450.0,
        "EV": 34.250999642857145,
        "Last Updated": "2025-09-03 00:46:22",
        "SetNumber": 504
    },
    {
        "Set Name": "Legends Awakened",
        "Adj. EV": 0.10300234248413401,
        "Pack Value": 255.745,
        "EV": 26.342334078604853,
        "Last Updated": "2025-09-03 00:46:22",
        "SetNumber": 505
    },
    {
        "Set Name": "Stormfront",
        "Adj. EV": 0.08256178423941402,
        "Pack Value": 299.99,
        "EV": 24.76770965398181,
        "Last Updated": "2025-09-03 00:46:22",
        "SetNumber": 506
    },
    {
        "Set Name": "Platinum",
        "Adj. EV": 0.14624675523932257,
        "Pack Value": 145.32,
        "EV": 21.252578471378357,
        "Last Updated": "2025-09-03 00:46:22",
        "SetNumber": 507
    },
    {
        "Set Name": "Rising Rivals",
        "Adj. EV": 0.14990607779547227,
        "Pack Value": 199.99,
        "EV": 29.9797164983165,
        "Last Updated": "2025-09-03 00:46:22",
        "SetNumber": 508
    },
    {
        "Set Name": "Supreme Victors",
        "Adj. EV": 0.10785622069926912,
        "Pack Value": 304.63,
        "EV": 32.85624051161835,
        "Last Updated": "2025-09-03 00:46:22",
        "SetNumber": 509
    },
    {
        "Set Name": "Arceus",
        "Adj. EV": 0.15000512164899168,
        "Pack Value": 179.99,
        "EV": 26.999421845602015,
        "Last Updated": "2025-09-03 00:46:22",
        "SetNumber": 510
    },
    {
        "Set Name": "HeartGold SoulSilver",
        "Adj. EV": 0.2181268949959884,
        "Pack Value": 287.5,
        "EV": 62.711482311346664,
        "Last Updated": "2025-09-03 00:46:22",
        "SetNumber": 600
    },
    {
        "Set Name": "Unleashed",
        "Adj. EV": 0.15022029858260086,
        "Pack Value": 174.99,
        "EV": 26.287050048969324,
        "Last Updated": "2025-09-03 00:46:22",
        "SetNumber": 601
    },
    {
        "Set Name": "Undaunted",
        "Adj. EV": 0.18949690087025534,
        "Pack Value": 201.51,
        "EV": 38.18552049436515,
        "Last Updated": "2025-09-03 00:46:22",
        "SetNumber": 602
    },
    {
        "Set Name": "Triumphant",
        "Adj. EV": 0.20561070829766231,
        "Pack Value": 130.0,
        "EV": 26.7293920786961,
        "Last Updated": "2025-09-03 00:46:22",
        "SetNumber": 603
    },
    {
        "Set Name": "Call of Legends",
        "Adj. EV": 0.16740116204125358,
        "Pack Value": 368.33,
        "EV": 61.65887001465493,
        "Last Updated": "2025-09-03 00:46:22",
        "SetNumber": 604
    },
    {
        "Set Name": "Black and White",
        "Adj. EV": 0.1726139318895236,
        "Pack Value": 79.58,
        "EV": 13.736616699768287,
        "Last Updated": "2025-09-03 00:46:22",
        "SetNumber": 700
    },
    {
        "Set Name": "Emerging Powers",
        "Adj. EV": 0.07040316889489685,
        "Pack Value": 76.96,
        "EV": 5.418227878151261,
        "Last Updated": "2025-09-03 00:46:22",
        "SetNumber": 701
    },
    {
        "Set Name": "Noble Victories",
        "Adj. EV": 0.12960855574638433,
        "Pack Value": 116.48,
        "EV": 15.096804573338847,
        "Last Updated": "2025-09-03 00:46:22",
        "SetNumber": 702
    },
    {
        "Set Name": "Next Destinies",
        "Adj. EV": 0.10464115173411186,
        "Pack Value": 110.56,
        "EV": 11.569125735723407,
        "Last Updated": "2025-09-03 00:46:22",
        "SetNumber": 703
    },
    {
        "Set Name": "Dark Explorers",
        "Adj. EV": 0.07693148527041509,
        "Pack Value": 350.0,
        "EV": 26.926019844645282,
        "Last Updated": "2025-09-03 00:46:22",
        "SetNumber": 704
    },
    {
        "Set Name": "Dragons Exalted",
        "Adj. EV": 0.12074574157231965,
        "Pack Value": 150.5,
        "EV": 18.172234106634107,
        "Last Updated": "2025-09-03 00:46:22",
        "SetNumber": 705
    },
    {
        "Set Name": "Boundaries Crossed",
        "Adj. EV": 0.12745239010743784,
        "Pack Value": 125.21,
        "EV": 15.958313765352292,
        "Last Updated": "2025-09-03 00:46:22",
        "SetNumber": 706
    },
    {
        "Set Name": "Plasma Storm",
        "Adj. EV": 0.06898724525177939,
        "Pack Value": 287.73,
        "EV": 19.849700076294486,
        "Last Updated": "2025-09-03 00:46:22",
        "SetNumber": 707
    },
    {
        "Set Name": "Plasma Freeze",
        "Adj. EV": 0.14154559231599706,
        "Pack Value": 148.25,
        "EV": 20.984134060846564,
        "Last Updated": "2025-09-03 00:46:22",
        "SetNumber": 708
    },
    {
        "Set Name": "Plasma Blast",
        "Adj. EV": 0.12645586950438328,
        "Pack Value": 89.35,
        "EV": 11.298831940216646,
        "Last Updated": "2025-09-03 00:46:22",
        "SetNumber": 709
    },
    {
        "Set Name": "Legendary Treasures",
        "Adj. EV": 0.26458809157696417,
        "Pack Value": 152.66,
        "EV": 40.39201806013935,
        "Last Updated": "2025-09-03 00:46:22",
        "SetNumber": 710
    },
    {
        "Set Name": "XY Base Set",
        "Adj. EV": 0.13731014721366844,
        "Pack Value": 52.38,
        "EV": 7.192305511051954,
        "Last Updated": "2025-09-03 00:46:22",
        "SetNumber": 800
    },
    {
        "Set Name": "XY - Flashfire",
        "Adj. EV": 0.12411780672837648,
        "Pack Value": 112.77,
        "EV": 13.996765064759016,
        "Last Updated": "2025-09-03 00:46:22",
        "SetNumber": 801
    },
    {
        "Set Name": "XY - Furious Fists",
        "Adj. EV": 0.21311501739813532,
        "Pack Value": 49.63,
        "EV": 10.576898313469457,
        "Last Updated": "2025-09-03 00:46:22",
        "SetNumber": 802
    },
    {
        "Set Name": "XY - Phantom Forces",
        "Adj. EV": 0.154234986635866,
        "Pack Value": 109.29,
        "EV": 16.856341689433794,
        "Last Updated": "2025-09-03 00:46:22",
        "SetNumber": 803
    },
    {
        "Set Name": "XY - Primal Clash",
        "Adj. EV": 0.20178909881688256,
        "Pack Value": 46.43,
        "EV": 9.369067858067858,
        "Last Updated": "2025-09-03 00:46:22",
        "SetNumber": 804
    },
    {
        "Set Name": "XY - Roaring Skies",
        "Adj. EV": 0.20018802624392973,
        "Pack Value": 49.09,
        "EV": 9.82723020831451,
        "Last Updated": "2025-09-03 00:46:22",
        "SetNumber": 805
    },
    {
        "Set Name": "XY - Ancient Origins",
        "Adj. EV": 0.21388868991185692,
        "Pack Value": 77.19,
        "EV": 16.510067974296234,
        "Last Updated": "2025-09-03 00:46:22",
        "SetNumber": 806
    },
    {
        "Set Name": "XY - BREAKthrough",
        "Adj. EV": 0.44594441055618533,
        "Pack Value": 31.06,
        "EV": 13.851033391875117,
        "Last Updated": "2025-09-03 00:46:22",
        "SetNumber": 807
    },
    {
        "Set Name": "XY - BREAKpoint",
        "Adj. EV": 0.4258249135906515,
        "Pack Value": 28.19,
        "EV": 12.004004314120467,
        "Last Updated": "2025-09-03 00:46:22",
        "SetNumber": 808
    },
    {
        "Set Name": "XY - Fates Collide",
        "Adj. EV": 0.3070411783530939,
        "Pack Value": 28.94,
        "EV": 8.885771701538538,
        "Last Updated": "2025-09-03 00:46:22",
        "SetNumber": 809
    },
    {
        "Set Name": "XY - Steam Siege",
        "Adj. EV": 0.2997035412103316,
        "Pack Value": 19.44,
        "EV": 5.826236841128847,
        "Last Updated": "2025-09-03 00:46:22",
        "SetNumber": 810
    },
    {
        "Set Name": "XY - Evolutions",
        "Adj. EV": 0.295009491282392,
        "Pack Value": 42.45,
        "EV": 12.523152904937541,
        "Last Updated": "2025-09-03 00:46:22",
        "SetNumber": 811
    },
    {
        "Set Name": "SM Base Set",
        "Adj. EV": 0.21286418134508842,
        "Pack Value": 14.56,
        "EV": 3.0993024803844875,
        "Last Updated": "2025-09-03 00:46:22",
        "SetNumber": 900
    },
    {
        "Set Name": "SM - Guardians Rising",
        "Adj. EV": 0.14841259476065394,
        "Pack Value": 22.9,
        "EV": 3.398648420018975,
        "Last Updated": "2025-09-03 00:46:22",
        "SetNumber": 901
    },
    {
        "Set Name": "SM - Burning Shadows",
        "Adj. EV": 0.1967145543257967,
        "Pack Value": 19.91,
        "EV": 3.9165867766266125,
        "Last Updated": "2025-09-03 00:46:22",
        "SetNumber": 902
    },
    {
        "Set Name": "SM - Crimson Invasion",
        "Adj. EV": 0.2623930121311273,
        "Pack Value": 12.8,
        "EV": 3.3586305552784297,
        "Last Updated": "2025-09-03 00:46:22",
        "SetNumber": 903
    },
    {
        "Set Name": "SM - Ultra Prism",
        "Adj. EV": 0.24327318010087431,
        "Pack Value": 33.19,
        "EV": 8.074236847548018,
        "Last Updated": "2025-09-03 00:46:22",
        "SetNumber": 904
    },
    {
        "Set Name": "SM - Forbidden Light",
        "Adj. EV": 0.29973866325666026,
        "Pack Value": 22.99,
        "EV": 6.8909918682706195,
        "Last Updated": "2025-09-03 00:46:22",
        "SetNumber": 905
    },
    {
        "Set Name": "SM - Celestial Storm",
        "Adj. EV": 0.15007908415775986,
        "Pack Value": 42.92,
        "EV": 6.441394292051053,
        "Last Updated": "2025-09-03 00:46:22",
        "SetNumber": 906
    },
    {
        "Set Name": "SM - Lost Thunder",
        "Adj. EV": 0.26056257547129374,
        "Pack Value": 28.22,
        "EV": 7.353075879799909,
        "Last Updated": "2025-09-03 00:46:22",
        "SetNumber": 907
    },
    {
        "Set Name": "SM - Team Up",
        "Adj. EV": 0.10958088419268391,
        "Pack Value": 180.62,
        "EV": 19.792499302882568,
        "Last Updated": "2025-09-03 00:46:22",
        "SetNumber": 908
    },
    {
        "Set Name": "SM - Unbroken Bonds",
        "Adj. EV": 0.2000687029762121,
        "Pack Value": 48.59,
        "EV": 9.721338277614146,
        "Last Updated": "2025-09-03 00:46:22",
        "SetNumber": 909
    },
    {
        "Set Name": "SM - Unified Minds",
        "Adj. EV": 0.2024477879649427,
        "Pack Value": 52.21,
        "EV": 10.569799009649659,
        "Last Updated": "2025-09-03 00:46:22",
        "SetNumber": 910
    },
    {
        "Set Name": "SM - Cosmic Eclipse",
        "Adj. EV": 0.2342367408654811,
        "Pack Value": 59.73,
        "EV": 13.990960531895185,
        "Last Updated": "2025-09-03 00:46:22",
        "SetNumber": 911
    },
    {
        "Set Name": "SWSH01: Sword & Shield Base Set",
        "Adj. EV": 0.3012654368593331,
        "Pack Value": 8.41,
        "EV": 2.5336423239869914,
        "Last Updated": "2025-09-03 00:46:22",
        "SetNumber": 1000
    },
    {
        "Set Name": "SWSH02: Rebel Clash",
        "Adj. EV": 0.3139422672568897,
        "Pack Value": 7.46,
        "EV": 2.342009313736397,
        "Last Updated": "2025-09-03 00:46:22",
        "SetNumber": 1001
    },
    {
        "Set Name": "SWSH03: Darkness Ablaze",
        "Adj. EV": 0.26192820920047344,
        "Pack Value": 7.23,
        "EV": 1.893740952519423,
        "Last Updated": "2025-09-03 00:46:22",
        "SetNumber": 1002
    },
    {
        "Set Name": "SWSH04: Vivid Voltage",
        "Adj. EV": 0.35659625272192513,
        "Pack Value": 6.48,
        "EV": 2.310743717638075,
        "Last Updated": "2025-09-03 00:46:22",
        "SetNumber": 1003
    },
    {
        "Set Name": "SWSH05: Battle Styles",
        "Adj. EV": 0.3093379149972208,
        "Pack Value": 6.13,
        "EV": 1.8962414189329635,
        "Last Updated": "2025-09-03 00:46:22",
        "SetNumber": 1004
    },
    {
        "Set Name": "SWSH06: Chilling Reign",
        "Adj. EV": 0.2525040208463871,
        "Pack Value": 8.61,
        "EV": 2.174059619487393,
        "Last Updated": "2025-09-03 00:46:22",
        "SetNumber": 1005
    },
    {
        "Set Name": "SWSH07: Evolving Skies",
        "Adj. EV": 0.20647052137097038,
        "Pack Value": 29.17,
        "EV": 6.022745108391207,
        "Last Updated": "2025-09-03 00:46:22",
        "SetNumber": 1006
    },
    {
        "Set Name": "SWSH08: Fusion Strike",
        "Adj. EV": 0.2345370222019266,
        "Pack Value": 12.17,
        "EV": 2.854315560197447,
        "Last Updated": "2025-09-03 00:46:22",
        "SetNumber": 1007
    },
    {
        "Set Name": "SWSH09: Brilliant Stars",
        "Adj. EV": 0.6561003351858112,
        "Pack Value": 7.31,
        "EV": 4.7960934502082795,
        "Last Updated": "2025-09-03 00:46:22",
        "SetNumber": 1100
    },
    {
        "Set Name": "SWSH10: Astral Radiance",
        "Adj. EV": 0.4809161217417241,
        "Pack Value": 6.6,
        "EV": 3.174046403495379,
        "Last Updated": "2025-09-03 00:46:22",
        "SetNumber": 1101
    },
    {
        "Set Name": "SWSH11: Lost Origin",
        "Adj. EV": 0.3711121495863062,
        "Pack Value": 10.36,
        "EV": 3.8447218697141317,
        "Last Updated": "2025-09-03 00:46:22",
        "SetNumber": 1102
    },
    {
        "Set Name": "SWSH12: Silver Tempest",
        "Adj. EV": 0.4345073124987037,
        "Pack Value": 7.33,
        "EV": 3.1849386006154985,
        "Last Updated": "2025-09-03 00:46:22",
        "SetNumber": 1103
    },
    {
        "Set Name": "SV01: Scarlet & Violet Base Set",
        "Adj. EV": 0.41857121038264966,
        "Pack Value": 6.48,
        "EV": 2.71234144327957,
        "Last Updated": "2025-09-03 00:46:22",
        "SetNumber": 1200
    },
    {
        "Set Name": "SV02: Paldea Evolved",
        "Adj. EV": 0.40408505941651957,
        "Pack Value": 8.73,
        "EV": 3.527662568706216,
        "Last Updated": "2025-09-03 00:46:22",
        "SetNumber": 1201
    },
    {
        "Set Name": "SV03: Obsidian Flames",
        "Adj. EV": 0.44767395858627396,
        "Pack Value": 6.98,
        "EV": 3.1247642309321924,
        "Last Updated": "2025-09-03 00:46:22",
        "SetNumber": 1202
    },
    {
        "Set Name": "SV04: Paradox Rift",
        "Adj. EV": 0.4651128262539988,
        "Pack Value": 6.1,
        "EV": 2.8371882401493926,
        "Last Updated": "2025-09-03 00:46:22",
        "SetNumber": 1203
    },
    {
        "Set Name": "SV05: Temporal Forces",
        "Adj. EV": 0.461119625015195,
        "Pack Value": 6.36,
        "EV": 2.93272081509664,
        "Last Updated": "2025-09-03 00:46:22",
        "SetNumber": 1204
    },
    {
        "Set Name": "SV06: Twilight Masquerade",
        "Adj. EV": 0.44532541394718717,
        "Pack Value": 7.02,
        "EV": 3.1261844059092536,
        "Last Updated": "2025-09-03 00:46:22",
        "SetNumber": 1205
    },
    {
        "Set Name": "SV07: Stellar Crown",
        "Adj. EV": 0.4241862428945733,
        "Pack Value": 6.2,
        "EV": 2.6299547059463544,
        "Last Updated": "2025-09-03 00:46:22",
        "SetNumber": 1206
    },
    {
        "Set Name": "SV08: Surging Sparks",
        "Adj. EV": 0.4172873873101641,
        "Pack Value": 6.53,
        "EV": 2.724886639135372,
        "Last Updated": "2025-09-03 00:46:22",
        "SetNumber": 1207
    },
    {
        "Set Name": "SV09: Journey Together",
        "Adj. EV": 0.5234616486573804,
        "Pack Value": 5.86,
        "EV": 3.0674852611322496,
        "Last Updated": "2025-09-03 00:46:22",
        "SetNumber": 1208
    },
    {
        "Set Name": "SV10: Destined Rivals",
        "Adj. EV": 0.5816594668229821,
        "Pack Value": 7.92,
        "EV": 4.606742977238018,
        "Last Updated": "2025-09-03 00:46:22",
        "SetNumber": 1209
    },
    {
        "Set Name": "Dragon Vault",
        "Adj. EV": 0.1379668339515601,
        "Pack Value": 183.32,
        "EV": 25.292079999999995,
        "Last Updated": "2025-09-03 00:46:22",
        "SetNumber": 705.5
    },
    {
        "Set Name": "Double Crisis",
        "Adj. EV": 0.358584099222588,
        "Pack Value": 178.39,
        "EV": 63.96781746031746,
        "Last Updated": "2025-09-03 00:46:22",
        "SetNumber": 804.5
    },
    {
        "Set Name": "Shining Legends",
        "Adj. EV": 0.19101901480833297,
        "Pack Value": 56.27,
        "EV": 10.748639963264896,
        "Last Updated": "2025-09-03 00:46:22",
        "SetNumber": 902.5
    },
    {
        "Set Name": "Dragon Majesty",
        "Adj. EV": 0.20223557032819614,
        "Pack Value": 49.37,
        "EV": 9.984370107103043,
        "Last Updated": "2025-09-03 00:46:22",
        "SetNumber": 906.5
    },
    {
        "Set Name": "Champions Path",
        "Adj. EV": 0.22286076444706732,
        "Pack Value": 14.23,
        "EV": 3.171308678081768,
        "Last Updated": "2025-09-03 00:46:22",
        "SetNumber": 1002.5
    },
    {
        "Set Name": "Pokemon Go",
        "Adj. EV": 0.4544389012732691,
        "Pack Value": 7.83,
        "EV": 3.558256596969697,
        "Last Updated": "2025-09-03 00:46:22",
        "SetNumber": 1101.5
    },
    {
        "Set Name": "Pokemon 151",
        "Adj. EV": 0.565035245000701,
        "Pack Value": 12.77,
        "EV": 7.215500078658952,
        "Last Updated": "2025-09-03 00:46:22",
        "SetNumber": 1202.5
    },
    {
        "Set Name": "Paldean Fates",
        "Adj. EV": 0.3529261757511684,
        "Pack Value": 14.64,
        "EV": 5.166839212997106,
        "Last Updated": "2025-09-03 00:46:22",
        "SetNumber": 1203.5
    },
    {
        "Set Name": "Shrouded Fable",
        "Adj. EV": 0.6184797445764594,
        "Pack Value": 6.88,
        "EV": 4.25514064268604,
        "Last Updated": "2025-09-03 00:46:22",
        "SetNumber": 1205.5
    },
    {
        "Set Name": "Hidden Fates",
        "Adj. EV": 0.35915143323874993,
        "Pack Value": 34.35,
        "EV": 12.33685173175106,
        "Last Updated": "2025-09-03 00:46:22",
        "SetNumber": 910.5
    },
    {
        "Set Name": "Shining Fates",
        "Adj. EV": 0.235474785516289,
        "Pack Value": 11.16,
        "EV": 2.6278986063617853,
        "Last Updated": "2025-09-03 00:46:22",
        "SetNumber": 1003.5
    },
    {
        "Set Name": "Generations",
        "Adj. EV": 0.2352255975680525,
        "Pack Value": 192.09,
        "EV": 45.18448503684721,
        "Last Updated": "2025-09-03 00:46:22",
        "SetNumber": 808.5
    },
    {
        "Set Name": "Crown Zenith",
        "Adj. EV": 0.5352417140752884,
        "Pack Value": 11.45,
        "EV": 6.128517626162052,
        "Last Updated": "2025-09-03 00:46:22",
        "SetNumber": 1103.5
    },
    {
        "Set Name": "Celebrations",
        "Adj. EV": 0.501663416327546,
        "Pack Value": 17.22,
        "EV": 8.638644029160341,
        "Last Updated": "2025-09-03 00:46:22",
        "SetNumber": 1006.5
    },
    {
        "Set Name": "Prismatic Evolutions",
        "Adj. EV": 0.4692176601337954,
        "Pack Value": 9.39,
        "EV": 4.405953828656339,
        "Last Updated": "2025-09-03 00:46:22",
        "SetNumber": 1207.5
    }
]