[
    {
        "Set Name": "Base Set",
        "Adj. EV": 0.08126508396534886,
        "Pack Value": 464.54,
        "EV": 37.75088210526316,
        "Last Updated": "2025-11-03 20:14:07",
        "SetNumber": 100
    },
    {
        "Set Name": "Jungle",
        "Adj. EV": 0.09814348428835491,
        "Pack Value": 232.63,
        "EV": 22.83111875,
        "Last Updated": "2025-11-03 20:14:07",
        "SetNumber": 101
    },
    {
        "Set Name": "Fossil",
        "Adj. EV": 0.09953527717782577,
        "Pack Value": 236.13,
        "EV": 23.503265,
        "Last Updated": "2025-11-03 20:14:07",
        "SetNumber": 102
    },
    {
        "Set Name": "Base Set 2",
        "Adj. EV": 0.09924211359150616,
        "Pack Value": 251.88,
        "EV": 24.99710357142857,
        "Last Updated": "2025-11-03 20:14:07",
        "SetNumber": 103
    },
    {
        "Set Name": "Team Rocket",
        "Adj. EV": 0.14894549450906575,
        "Pack Value": 271.73,
        "EV": 40.47295922294844,
        "Last Updated": "2025-11-03 20:14:07",
        "SetNumber": 104
    },
    {
        "Set Name": "Gym Heroes",
        "Adj. EV": 0.1314348169202093,
        "Pack Value": 284.0,
        "EV": 37.32748800533944,
        "Last Updated": "2025-11-03 20:14:07",
        "SetNumber": 105
    },
    {
        "Set Name": "Gym Challenge",
        "Adj. EV": 0.22823062277856826,
        "Pack Value": 247.99,
        "EV": 56.598912142857145,
        "Last Updated": "2025-11-03 20:14:07",
        "SetNumber": 106
    },
    {
        "Set Name": "Neo Genesis",
        "Adj. EV": 0.05957526156513023,
        "Pack Value": 580.0,
        "EV": 34.553651707775536,
        "Last Updated": "2025-11-03 20:14:07",
        "SetNumber": 107
    },
    {
        "Set Name": "Neo Discovery",
        "Adj. EV": 0.11044684817065653,
        "Pack Value": 344.44,
        "EV": 38.042312383900935,
        "Last Updated": "2025-11-03 20:14:07",
        "SetNumber": 108
    },
    {
        "Set Name": "Neo Revelation",
        "Adj. EV": 0.15546572763692373,
        "Pack Value": 450.0,
        "EV": 69.95957743661567,
        "Last Updated": "2025-11-03 20:14:07",
        "SetNumber": 109
    },
    {
        "Set Name": "Neo Destiny",
        "Adj. EV": 0.2101966105414269,
        "Pack Value": 799.0,
        "EV": 167.9470918226001,
        "Last Updated": "2025-11-03 20:14:07",
        "SetNumber": 110
    },
    {
        "Set Name": "Legendary Collection",
        "Adj. EV": 0.06942868543403997,
        "Pack Value": 2499.99,
        "EV": 173.57101929824557,
        "Last Updated": "2025-11-03 20:14:07",
        "SetNumber": 200
    },
    {
        "Set Name": "Expedition",
        "Adj. EV": 0.12142024830756985,
        "Pack Value": 1200.0,
        "EV": 145.70429796908383,
        "Last Updated": "2025-11-03 20:14:07",
        "SetNumber": 201
    },
    {
        "Set Name": "Aquapolis",
        "Adj. EV": 0.1520738949753746,
        "Pack Value": 1050.99,
        "EV": 159.82814288016897,
        "Last Updated": "2025-11-03 20:14:07",
        "SetNumber": 202
    },
    {
        "Set Name": "Skyridge",
        "Adj. EV": 0.12220157147133932,
        "Pack Value": 2500.0,
        "EV": 305.5039286783483,
        "Last Updated": "2025-11-03 20:14:07",
        "SetNumber": 203
    },
    {
        "Set Name": "Ruby and Sapphire",
        "Adj. EV": 0.04968073195862175,
        "Pack Value": 599.99,
        "EV": 29.807942367853464,
        "Last Updated": "2025-11-03 20:14:07",
        "SetNumber": 300
    },
    {
        "Set Name": "Sandstorm",
        "Adj. EV": 0.0832473523283042,
        "Pack Value": 496.95,
        "EV": 41.36977173955077,
        "Last Updated": "2025-11-03 20:14:07",
        "SetNumber": 301
    },
    {
        "Set Name": "Dragon",
        "Adj. EV": 0.054365656694229485,
        "Pack Value": 1047.5,
        "EV": 56.948025387205384,
        "Last Updated": "2025-11-03 20:14:07",
        "SetNumber": 302
    },
    {
        "Set Name": "Team Magma vs Team Aqua",
        "Adj. EV": 0.1826317208193042,
        "Pack Value": 300.0,
        "EV": 54.78951624579126,
        "Last Updated": "2025-11-03 20:14:07",
        "SetNumber": 303
    },
    {
        "Set Name": "Hidden Legends",
        "Adj. EV": 0.12914252512116003,
        "Pack Value": 319.94,
        "EV": 41.31785948726394,
        "Last Updated": "2025-11-03 20:14:07",
        "SetNumber": 304
    },
    {
        "Set Name": "FireRed & LeafGreen",
        "Adj. EV": 0.09751043653115558,
        "Pack Value": 622.48,
        "EV": 60.69829653191373,
        "Last Updated": "2025-11-03 20:14:07",
        "SetNumber": 305
    },
    {
        "Set Name": "Emerald",
        "Adj. EV": 0.07513228923716998,
        "Pack Value": 725.0,
        "EV": 54.47090969694824,
        "Last Updated": "2025-11-03 20:14:07",
        "SetNumber": 306
    },
    {
        "Set Name": "Team Rocket Returns",
        "Adj. EV": 0.06066995291069339,
        "Pack Value": 1999.99,
        "EV": 121.33929912185766,
        "Last Updated": "2025-11-03 20:14:07",
        "SetNumber": 400
    },
    {
        "Set Name": "Deoxys",
        "Adj. EV": 0.030218532856321277,
        "Pack Value": 1599.99,
        "EV": 48.34935038478548,
        "Last Updated": "2025-11-03 20:14:07",
        "SetNumber": 401
    },
    {
        "Set Name": "Unseen Forces",
        "Adj. EV": 0.0939321880101343,
        "Pack Value": 699.95,
        "EV": 65.7478349976935,
        "Last Updated": "2025-11-03 20:14:07",
        "SetNumber": 402
    },
    {
        "Set Name": "Delta Species",
        "Adj. EV": 0.16171010898756877,
        "Pack Value": 749.95,
        "EV": 121.2744962352272,
        "Last Updated": "2025-11-03 20:14:07",
        "SetNumber": 403
    },
    {
        "Set Name": "Legend Maker",
        "Adj. EV": 0.10478392011489547,
        "Pack Value": 464.0,
        "EV": 48.619738933311496,
        "Last Updated": "2025-11-03 20:14:07",
        "SetNumber": 404
    },
    {
        "Set Name": "Holon Phantoms",
        "Adj. EV": 0.1098453779986035,
        "Pack Value": 683.3,
        "EV": 75.05734678644576,
        "Last Updated": "2025-11-03 20:14:07",
        "SetNumber": 405
    },
    {
        "Set Name": "Crystal Guardians",
        "Adj. EV": 0.045600740067124314,
        "Pack Value": 1200.0,
        "EV": 54.72088808054917,
        "Last Updated": "2025-11-03 20:14:07",
        "SetNumber": 406
    },
    {
        "Set Name": "Dragon Frontiers",
        "Adj. EV": 0.06928766130095243,
        "Pack Value": 899.95,
        "EV": 62.355430787792145,
        "Last Updated": "2025-11-03 20:14:07",
        "SetNumber": 407
    },
    {
        "Set Name": "Power Keepers",
        "Adj. EV": 0.07135451628936013,
        "Pack Value": 616.33,
        "EV": 43.97792902462133,
        "Last Updated": "2025-11-03 20:14:07",
        "SetNumber": 408
    },
    {
        "Set Name": "Diamond and Pearl",
        "Adj. EV": 0.1505694349424728,
        "Pack Value": 154.75,
        "EV": 23.300620057347665,
        "Last Updated": "2025-11-03 20:14:07",
        "SetNumber": 500
    },
    {
        "Set Name": "Mysterious Treasures",
        "Adj. EV": 0.1393941558798725,
        "Pack Value": 119.4,
        "EV": 16.64366221205678,
        "Last Updated": "2025-11-03 20:14:07",
        "SetNumber": 501
    },
    {
        "Set Name": "Secret Wonders",
        "Adj. EV": 0.07640223628015375,
        "Pack Value": 312.0,
        "EV": 23.837497719407967,
        "Last Updated": "2025-11-03 20:14:07",
        "SetNumber": 502
    },
    {
        "Set Name": "Great Encounters",
        "Adj. EV": 0.09483205174804807,
        "Pack Value": 211.99,
        "EV": 20.10344665006871,
        "Last Updated": "2025-11-03 20:14:07",
        "SetNumber": 503
    },
    {
        "Set Name": "Majestic Dawn",
        "Adj. EV": 0.08406997627865961,
        "Pack Value": 450.0,
        "EV": 37.831489325396824,
        "Last Updated": "2025-11-03 20:14:07",
        "SetNumber": 504
    },
    {
        "Set Name": "Legends Awakened",
        "Adj. EV": 0.11887367835240008,
        "Pack Value": 244.0,
        "EV": 29.00517751798562,
        "Last Updated": "2025-11-03 20:14:07",
        "SetNumber": 505
    },
    {
        "Set Name": "Stormfront",
        "Adj. EV": 0.09193368793886056,
        "Pack Value": 287.5,
        "EV": 26.43093528242241,
        "Last Updated": "2025-11-03 20:14:07",
        "SetNumber": 506
    },
    {
        "Set Name": "Platinum",
        "Adj. EV": 0.13311681671111555,
        "Pack Value": 169.99,
        "EV": 22.628527672722534,
        "Last Updated": "2025-11-03 20:14:07",
        "SetNumber": 507
    },
    {
        "Set Name": "Rising Rivals",
        "Adj. EV": 0.114585189929599,
        "Pack Value": 275.0,
        "EV": 31.510927230639723,
        "Last Updated": "2025-11-03 20:14:07",
        "SetNumber": 508
    },
    {
        "Set Name": "Supreme Victors",
        "Adj. EV": 0.11190241139846442,
        "Pack Value": 319.75,
        "EV": 35.780796044659,
        "Last Updated": "2025-11-03 20:14:07",
        "SetNumber": 509
    },
    {
        "Set Name": "Arceus",
        "Adj. EV": 0.12543179131327808,
        "Pack Value": 229.35,
        "EV": 28.767781337700328,
        "Last Updated": "2025-11-03 20:14:07",
        "SetNumber": 510
    },
    {
        "Set Name": "HeartGold SoulSilver",
        "Adj. EV": 0.1907754881063283,
        "Pack Value": 357.5,
        "EV": 68.20223699801237,
        "Last Updated": "2025-11-03 20:14:07",
        "SetNumber": 600
    },
    {
        "Set Name": "Unleashed",
        "Adj. EV": 0.1621212613578606,
        "Pack Value": 174.99,
        "EV": 28.369599525012024,
        "Last Updated": "2025-11-03 20:14:07",
        "SetNumber": 601
    },
    {
        "Set Name": "Undaunted",
        "Adj. EV": 0.22695493828445473,
        "Pack Value": 201.51,
        "EV": 45.73368961370047,
        "Last Updated": "2025-11-03 20:14:07",
        "SetNumber": 602
    },
    {
        "Set Name": "Triumphant",
        "Adj. EV": 0.10453888521857038,
        "Pack Value": 299.99,
        "EV": 31.360620176718932,
        "Last Updated": "2025-11-03 20:14:07",
        "SetNumber": 603
    },
    {
        "Set Name": "Call of Legends",
        "Adj. EV": 0.16029488250922483,
        "Pack Value": 416.66,
        "EV": 66.78846574629362,
        "Last Updated": "2025-11-03 20:14:07",
        "SetNumber": 604
    },
    {
        "Set Name": "Black and White",
        "Adj. EV": 0.1499388692992366,
        "Pack Value": 93.86,
        "EV": 14.073262272426348,
        "Last Updated": "2025-11-03 20:14:07",
        "SetNumber": 700
    },
    {
        "Set Name": "Emerging Powers",
        "Adj. EV": 0.07329943702111753,
        "Pack Value": 79.35,
        "EV": 5.816310327625676,
        "Last Updated": "2025-11-03 20:14:07",
        "SetNumber": 701
    },
    {
        "Set Name": "Noble Victories",
        "Adj. EV": 0.15234499795266818,
        "Pack Value": 105.95,
        "EV": 16.140952533085194,
        "Last Updated": "2025-11-03 20:14:07",
        "SetNumber": 702
    },
    {
        "Set Name": "Next Destinies",
        "Adj. EV": 0.08631274166195592,
        "Pack Value": 152.5,
        "EV": 13.162693103448278,
        "Last Updated": "2025-11-03 20:14:07",
        "SetNumber": 703
    },
    {
        "Set Name": "Dark Explorers",
        "Adj. EV": 0.08142652423808439,
        "Pack Value": 350.0,
        "EV": 28.499283483329535,
        "Last Updated": "2025-11-03 20:14:07",
        "SetNumber": 704
    },
    {
        "Set Name": "Dragons Exalted",
        "Adj. EV": 0.12007388296255626,
        "Pack Value": 164.92,
        "EV": 19.802584778184777,
        "Last Updated": "2025-11-03 20:14:07",
        "SetNumber": 705
    },
    {
        "Set Name": "Boundaries Crossed",
        "Adj. EV": 0.13993313331873394,
        "Pack Value": 127.33,
        "EV": 17.81768586547439,
        "Last Updated": "2025-11-03 20:14:07",
        "SetNumber": 706
    },
    {
        "Set Name": "Plasma Storm",
        "Adj. EV": 0.0754587564315401,
        "Pack Value": 290.31,
        "EV": 21.906431579640405,
        "Last Updated": "2025-11-03 20:14:07",
        "SetNumber": 707
    },
    {
        "Set Name": "Plasma Freeze",
        "Adj. EV": 0.12905342743764173,
        "Pack Value": 175.0,
        "EV": 22.5843498015873,
        "Last Updated": "2025-11-03 20:14:07",
        "SetNumber": 708
    },
    {
        "Set Name": "Plasma Blast",
        "Adj. EV": 0.127068803147411,
        "Pack Value": 106.1,
        "EV": 13.482000013940308,
        "Last Updated": "2025-11-03 20:14:07",
        "SetNumber": 709
    },
    {
        "Set Name": "Legendary Treasures",
        "Adj. EV": 0.2708339137661301,
        "Pack Value": 177.45,
        "EV": 48.05947799779978,
        "Last Updated": "2025-11-03 20:14:07",
        "SetNumber": 710
    },
    {
        "Set Name": "XY Base Set",
        "Adj. EV": 0.13396404517159424,
        "Pack Value": 56.48,
        "EV": 7.566289271291643,
        "Last Updated": "2025-11-03 20:14:07",
        "SetNumber": 800
    },
    {
        "Set Name": "XY - Flashfire",
        "Adj. EV": 0.11696276493912597,
        "Pack Value": 129.13,
        "EV": 15.103401836589336,
        "Last Updated": "2025-11-03 20:14:07",
        "SetNumber": 801
    },
    {
        "Set Name": "XY - Furious Fists",
        "Adj. EV": 0.22789937348456282,
        "Pack Value": 51.17,
        "EV": 11.66161094120508,
        "Last Updated": "2025-11-03 20:14:07",
        "SetNumber": 802
    },
    {
        "Set Name": "XY - Phantom Forces",
        "Adj. EV": 0.16575977865822944,
        "Pack Value": 132.21,
        "EV": 21.915100336404514,
        "Last Updated": "2025-11-03 20:14:07",
        "SetNumber": 803
    },
    {
        "Set Name": "XY - Primal Clash",
        "Adj. EV": 0.19727399783767113,
        "Pack Value": 51.67,
        "EV": 10.193147468272468,
        "Last Updated": "2025-11-03 20:14:07",
        "SetNumber": 804
    },
    {
        "Set Name": "XY - Roaring Skies",
        "Adj. EV": 0.17367732321278742,
        "Pack Value": 62.26,
        "EV": 10.813150143228144,
        "Last Updated": "2025-11-03 20:14:07",
        "SetNumber": 805
    },
    {
        "Set Name": "XY - Ancient Origins",
        "Adj. EV": 0.19289746141102562,
        "Pack Value": 101.45,
        "EV": 19.56944746014855,
        "Last Updated": "2025-11-03 20:14:07",
        "SetNumber": 806
    },
    {
        "Set Name": "XY - BREAKthrough",
        "Adj. EV": 0.44475646167570876,
        "Pack Value": 34.54,
        "EV": 15.36188818627898,
        "Last Updated": "2025-11-03 20:14:07",
        "SetNumber": 807
    },
    {
        "Set Name": "XY - BREAKpoint",
        "Adj. EV": 0.41831044336810225,
        "Pack Value": 32.21,
        "EV": 13.473779380886574,
        "Last Updated": "2025-11-03 20:14:07",
        "SetNumber": 808
    },
    {
        "Set Name": "XY - Fates Collide",
        "Adj. EV": 0.2784377578280054,
        "Pack Value": 37.68,
        "EV": 10.491534714959244,
        "Last Updated": "2025-11-03 20:14:07",
        "SetNumber": 809
    },
    {
        "Set Name": "XY - Steam Siege",
        "Adj. EV": 0.3087727398074814,
        "Pack Value": 19.85,
        "EV": 6.129138885178506,
        "Last Updated": "2025-11-03 20:14:07",
        "SetNumber": 810
    },
    {
        "Set Name": "XY - Evolutions",
        "Adj. EV": 0.2927957216611947,
        "Pack Value": 44.98,
        "EV": 13.169951560320538,
        "Last Updated": "2025-11-03 20:14:07",
        "SetNumber": 811
    },
    {
        "Set Name": "SM Base Set",
        "Adj. EV": 0.21889814026232218,
        "Pack Value": 14.61,
        "EV": 3.198101829232527,
        "Last Updated": "2025-11-03 20:14:07",
        "SetNumber": 900
    },
    {
        "Set Name": "SM - Guardians Rising",
        "Adj. EV": 0.14878822110304002,
        "Pack Value": 23.83,
        "EV": 3.5456233088854434,
        "Last Updated": "2025-11-03 20:14:07",
        "SetNumber": 901
    },
    {
        "Set Name": "SM - Burning Shadows",
        "Adj. EV": 0.16528725345636305,
        "Pack Value": 24.66,
        "EV": 4.075983670233913,
        "Last Updated": "2025-11-03 20:14:07",
        "SetNumber": 902
    },
    {
        "Set Name": "SM - Crimson Invasion",
        "Adj. EV": 0.2676918054105964,
        "Pack Value": 14.31,
        "EV": 3.830669735425635,
        "Last Updated": "2025-11-03 20:14:07",
        "SetNumber": 903
    },
    {
        "Set Name": "SM - Ultra Prism",
        "Adj. EV": 0.2209940324263293,
        "Pack Value": 39.11,
        "EV": 8.64307660819374,
        "Last Updated": "2025-11-03 20:14:07",
        "SetNumber": 904
    },
    {
        "Set Name": "SM - Forbidden Light",
        "Adj. EV": 0.31948288743058495,
        "Pack Value": 24.3,
        "EV": 7.763434164563215,
        "Last Updated": "2025-11-03 20:14:07",
        "SetNumber": 905
    },
    {
        "Set Name": "SM - Celestial Storm",
        "Adj. EV": 0.16437714526114422,
        "Pack Value": 44.33,
        "EV": 7.286838849426523,
        "Last Updated": "2025-11-03 20:14:07",
        "SetNumber": 906
    },
    {
        "Set Name": "SM - Lost Thunder",
        "Adj. EV": 0.2697040336932465,
        "Pack Value": 30.0,
        "EV": 8.091121010797396,
        "Last Updated": "2025-11-03 20:14:07",
        "SetNumber": 907
    },
    {
        "Set Name": "SM - Team Up",
        "Adj. EV": 0.11747699326279704,
        "Pack Value": 186.22,
        "EV": 21.876565685398063,
        "Last Updated": "2025-11-03 20:14:07",
        "SetNumber": 908
    },
    {
        "Set Name": "SM - Unbroken Bonds",
        "Adj. EV": 0.19098370043417445,
        "Pack Value": 56.48,
        "EV": 10.786759400522172,
        "Last Updated": "2025-11-03 20:14:07",
        "SetNumber": 909
    },
    {
        "Set Name": "SM - Unified Minds",
        "Adj. EV": 0.1847684316219345,
        "Pack Value": 62.04,
        "EV": 11.463033497824815,
        "Last Updated": "2025-11-03 20:14:07",
        "SetNumber": 910
    },
    {
        "Set Name": "SM - Cosmic Eclipse",
        "Adj. EV": 0.23904825306566166,
        "Pack Value": 66.51,
        "EV": 15.899099311397158,
        "Last Updated": "2025-11-03 20:14:07",
        "SetNumber": 911
    },
    {
        "Set Name": "SWSH01: Sword & Shield Base Set",
        "Adj. EV": 0.3436586209945559,
        "Pack Value": 7.63,
        "EV": 2.6221152781884616,
        "Last Updated": "2025-11-03 20:14:07",
        "SetNumber": 1000
    },
    {
        "Set Name": "SWSH02: Rebel Clash",
        "Adj. EV": 0.3434151101339415,
        "Pack Value": 7.37,
        "EV": 2.530969361687149,
        "Last Updated": "2025-11-03 20:14:07",
        "SetNumber": 1001
    },
    {
        "Set Name": "SWSH03: Darkness Ablaze",
        "Adj. EV": 0.2824237582748687,
        "Pack Value": 7.04,
        "EV": 1.9882632582550759,
        "Last Updated": "2025-11-03 20:14:07",
        "SetNumber": 1002
    },
    {
        "Set Name": "SWSH04: Vivid Voltage",
        "Adj. EV": 0.3073812969746838,
        "Pack Value": 7.46,
        "EV": 2.2930644754311413,
        "Last Updated": "2025-11-03 20:14:07",
        "SetNumber": 1003
    },
    {
        "Set Name": "SWSH05: Battle Styles",
        "Adj. EV": 0.2934569506994769,
        "Pack Value": 6.77,
        "EV": 1.9867035562354587,
        "Last Updated": "2025-11-03 20:14:07",
        "SetNumber": 1004
    },
    {
        "Set Name": "SWSH06: Chilling Reign",
        "Adj. EV": 0.26557543960024094,
        "Pack Value": 8.62,
        "EV": 2.2892602893540768,
        "Last Updated": "2025-11-03 20:14:07",
        "SetNumber": 1005
    },
    {
        "Set Name": "SWSH07: Evolving Skies",
        "Adj. EV": 0.259722076267657,
        "Pack Value": 30.03,
        "EV": 7.799453950317739,
        "Last Updated": "2025-11-03 20:14:07",
        "SetNumber": 1006
    },
    {
        "Set Name": "SWSH08: Fusion Strike",
        "Adj. EV": 0.24355519694544375,
        "Pack Value": 13.26,
        "EV": 3.229541911496584,
        "Last Updated": "2025-11-03 20:14:07",
        "SetNumber": 1007
    },
    {
        "Set Name": "SWSH09: Brilliant Stars",
        "Adj. EV": 0.6327503305887736,
        "Pack Value": 8.64,
        "EV": 5.4669628562870045,
        "Last Updated": "2025-11-03 20:14:07",
        "SetNumber": 1100
    },
    {
        "Set Name": "SWSH10: Astral Radiance",
        "Adj. EV": 0.4464592544475998,
        "Pack Value": 7.53,
        "EV": 3.3618381859904267,
        "Last Updated": "2025-11-03 20:14:07",
        "SetNumber": 1101
    },
    {
        "Set Name": "SWSH11: Lost Origin",
        "Adj. EV": 0.343838748703091,
        "Pack Value": 12.4,
        "EV": 4.263600483918329,
        "Last Updated": "2025-11-03 20:14:07",
        "SetNumber": 1102
    },
    {
        "Set Name": "SWSH12: Silver Tempest",
        "Adj. EV": 0.46424339665032976,
        "Pack Value": 7.92,
        "EV": 3.6768077014706115,
        "Last Updated": "2025-11-03 20:14:07",
        "SetNumber": 1103
    },
    {
        "Set Name": "SV01: Scarlet & Violet Base Set",
        "Adj. EV": 0.4270447828823159,
        "Pack Value": 6.81,
        "EV": 2.908174971428571,
        "Last Updated": "2025-11-03 20:14:07",
        "SetNumber": 1200
    },
    {
        "Set Name": "SV02: Paldea Evolved",
        "Adj. EV": 0.4082666435433599,
        "Pack Value": 9.62,
        "EV": 3.927525110887122,
        "Last Updated": "2025-11-03 20:14:07",
        "SetNumber": 1201
    },
    {
        "Set Name": "SV03: Obsidian Flames",
        "Adj. EV": 0.36627354048375543,
        "Pack Value": 7.92,
        "EV": 2.900886440631343,
        "Last Updated": "2025-11-03 20:14:07",
        "SetNumber": 1202
    },
    {
        "Set Name": "SV04: Paradox Rift",
        "Adj. EV": 0.4561956223425666,
        "Pack Value": 6.25,
        "EV": 2.8512226396410414,
        "Last Updated": "2025-11-03 20:14:07",
        "SetNumber": 1203
    },
    {
        "Set Name": "SV05: Temporal Forces",
        "Adj. EV": 0.47072070632970897,
        "Pack Value": 6.27,
        "EV": 2.951418828687275,
        "Last Updated": "2025-11-03 20:14:07",
        "SetNumber": 1204
    },
    {
        "Set Name": "SV06: Twilight Masquerade",
        "Adj. EV": 0.468403181990993,
        "Pack Value": 6.79,
        "EV": 3.1804576057188427,
        "Last Updated": "2025-11-03 20:14:07",
        "SetNumber": 1205
    },
    {
        "Set Name": "SV07: Stellar Crown",
        "Adj. EV": 0.3991334957746107,
        "Pack Value": 7.06,
        "EV": 2.8178824801687514,
        "Last Updated": "2025-11-03 20:14:07",
        "SetNumber": 1206
    },
    {
        "Set Name": "SV08: Surging Sparks",
        "Adj. EV": 0.45641411582187136,
        "Pack Value": 6.58,
        "EV": 3.0032048821079136,
        "Last Updated": "2025-11-03 20:14:07",
        "SetNumber": 1207
    },
    {
        "Set Name": "SV09: Journey Together",
        "Adj. EV": 0.428708166090721,
        "Pack Value": 6.52,
        "EV": 2.7951772429115005,
        "Last Updated": "2025-11-03 20:14:07",
        "SetNumber": 1208
    },
    {
        "Set Name": "SV10: Destined Rivals",
        "Adj. EV": 0.5801084739991453,
        "Pack Value": 7.8828,
        "EV": 4.5728790788404625,
        "Last Updated": "2025-11-03 20:14:07",
        "SetNumber": 1209
    },
    {
        "Set Name": "ME01: Mega Evolution",
        "Adj. EV": 96.9677045737943,
        "Pack Value": 0.04,
        "EV": 3.8787081829517716,
        "Last Updated": "2025-11-03 20:14:07",
        "SetNumber": 1210
    },
    {
        "Set Name": "Dragon Vault",
        "Adj. EV": 0.13707325366268314,
        "Pack Value": 199.99,
        "EV": 27.41328,
        "Last Updated": "2025-11-03 20:14:07",
        "SetNumber": 705.5
    },
    {
        "Set Name": "Double Crisis",
        "Adj. EV": 0.31071047464486173,
        "Pack Value": 262.22,
        "EV": 81.47450066137566,
        "Last Updated": "2025-11-03 20:14:07",
        "SetNumber": 804.5
    },
    {
        "Set Name": "Shining Legends",
        "Adj. EV": 0.18204826634811636,
        "Pack Value": 68.57,
        "EV": 12.483049623490338,
        "Last Updated": "2025-11-03 20:14:07",
        "SetNumber": 902.5
    },
    {
        "Set Name": "Dragon Majesty",
        "Adj. EV": 0.20448192272858878,
        "Pack Value": 53.92,
        "EV": 11.025665273525508,
        "Last Updated": "2025-11-03 20:14:07",
        "SetNumber": 906.5
    },
    {
        "Set Name": "Champions Path",
        "Adj. EV": 0.22758398246112937,
        "Pack Value": 15.52,
        "EV": 3.5321034077967277,
        "Last Updated": "2025-11-03 20:14:07",
        "SetNumber": 1002.5
    },
    {
        "Set Name": "Pokemon Go",
        "Adj. EV": 0.4734929044653264,
        "Pack Value": 8.32,
        "EV": 3.9394609651515156,
        "Last Updated": "2025-11-03 20:14:07",
        "SetNumber": 1101.5
    },
    {
        "Set Name": "Pokemon 151",
        "Adj. EV": 0.4547411348840629,
        "Pack Value": 16.45,
        "EV": 7.480491668842835,
        "Last Updated": "2025-11-03 20:14:07",
        "SetNumber": 1202.5
    },
    {
        "Set Name": "Paldean Fates",
        "Adj. EV": 0.3511592966642469,
        "Pack Value": 14.67,
        "EV": 5.151506882064502,
        "Last Updated": "2025-11-03 20:14:07",
        "SetNumber": 1203.5
    },
    {
        "Set Name": "Shrouded Fable",
        "Adj. EV": 0.5640451499940773,
        "Pack Value": 8.0,
        "EV": 4.512361199952618,
        "Last Updated": "2025-11-03 20:14:07",
        "SetNumber": 1205.5
    },
    {
        "Set Name": "Hidden Fates",
        "Adj. EV": 0.3614633279508717,
        "Pack Value": 35.47,
        "EV": 12.82110424241742,
        "Last Updated": "2025-11-03 20:14:07",
        "SetNumber": 910.5
    },
    {
        "Set Name": "Shining Fates",
        "Adj. EV": 0.2474984606068506,
        "Pack Value": 11.56,
        "EV": 2.861082204615193,
        "Last Updated": "2025-11-03 20:14:07",
        "SetNumber": 1003.5
    },
    {
        "Set Name": "Generations",
        "Adj. EV": 0.2574920352005067,
        "Pack Value": 192.61,
        "EV": 49.5955408999696,
        "Last Updated": "2025-11-03 20:14:07",
        "SetNumber": 808.5
    },
    {
        "Set Name": "Crown Zenith",
        "Adj. EV": 0.5359695617278458,
        "Pack Value": 13.23,
        "EV": 7.0908773016594004,
        "Last Updated": "2025-11-03 20:14:07",
        "SetNumber": 1103.5
    },
    {
        "Set Name": "Celebrations",
        "Adj. EV": 0.4122571065702048,
        "Pack Value": 19.4,
        "EV": 7.997787867461973,
        "Last Updated": "2025-11-03 20:14:07",
        "SetNumber": 1006.5
    },
    {
        "Set Name": "Prismatic Evolutions",
        "Adj. EV": 0.5234373175419494,
        "Pack Value": 8.75,
        "EV": 4.580076528492057,
        "Last Updated": "2025-11-03 20:14:07",
        "SetNumber": 1207.5
    },
    {
        "Set Name": "Black Bolt",
        "Adj. EV": 0.7323354153354475,
        "Pack Value": 8.02,
        "EV": 5.873330030990289,
        "Last Updated": "2025-11-03 20:14:07",
        "SetNumber": 1209.5
    },
    {
        "Set Name": "White Flare",
        "Adj. EV": 0.6626777315471484,
        "Pack Value": 8.53,
        "EV": 5.652641050097175,
        "Last Updated": "2025-11-03 20:14:07",
        "SetNumber": 1210.5
    }
]