[
    {
        "Set Name": "Base Set",
        "Adj. EV": 0.08117192284849684,
        "Pack Value": 465.25,
        "EV": 37.765237105263154,
        "Last Updated": "2025-10-03 15:11:34",
        "SetNumber": 100
    },
    {
        "Set Name": "Jungle",
        "Adj. EV": 0.09855915564823853,
        "Pack Value": 225.38,
        "EV": 22.2132625,
        "Last Updated": "2025-10-03 15:11:34",
        "SetNumber": 101
    },
    {
        "Set Name": "Fossil",
        "Adj. EV": 0.10084633848302346,
        "Pack Value": 229.14,
        "EV": 23.107929999999996,
        "Last Updated": "2025-10-03 15:11:34",
        "SetNumber": 102
    },
    {
        "Set Name": "Base Set 2",
        "Adj. EV": 0.09754281839056529,
        "Pack Value": 246.99,
        "EV": 24.09210071428572,
        "Last Updated": "2025-10-03 15:11:34",
        "SetNumber": 103
    },
    {
        "Set Name": "Team Rocket",
        "Adj. EV": 0.150213031817003,
        "Pack Value": 265.71,
        "EV": 39.91310468409586,
        "Last Updated": "2025-10-03 15:11:34",
        "SetNumber": 104
    },
    {
        "Set Name": "Gym Heroes",
        "Adj. EV": 0.12892352893102324,
        "Pack Value": 284.0,
        "EV": 36.6142822164106,
        "Last Updated": "2025-10-03 15:11:34",
        "SetNumber": 105
    },
    {
        "Set Name": "Gym Challenge",
        "Adj. EV": 0.22784584631868798,
        "Pack Value": 247.99,
        "EV": 56.50349142857144,
        "Last Updated": "2025-10-03 15:11:34",
        "SetNumber": 106
    },
    {
        "Set Name": "Neo Genesis",
        "Adj. EV": 0.059296904167746946,
        "Pack Value": 580.0,
        "EV": 34.39220441729323,
        "Last Updated": "2025-10-03 15:11:34",
        "SetNumber": 107
    },
    {
        "Set Name": "Neo Discovery",
        "Adj. EV": 0.10814902315527732,
        "Pack Value": 344.44,
        "EV": 37.25084953560372,
        "Last Updated": "2025-10-03 15:11:34",
        "SetNumber": 108
    },
    {
        "Set Name": "Neo Revelation",
        "Adj. EV": 0.1528808552036199,
        "Pack Value": 450.0,
        "EV": 68.79638484162896,
        "Last Updated": "2025-10-03 15:11:34",
        "SetNumber": 109
    },
    {
        "Set Name": "Neo Destiny",
        "Adj. EV": 0.20825134189700178,
        "Pack Value": 799.0,
        "EV": 166.39282217570442,
        "Last Updated": "2025-10-03 15:11:34",
        "SetNumber": 110
    },
    {
        "Set Name": "Legendary Collection",
        "Adj. EV": 0.06364404746207428,
        "Pack Value": 2499.99,
        "EV": 159.10948221471105,
        "Last Updated": "2025-10-03 15:11:34",
        "SetNumber": 200
    },
    {
        "Set Name": "Expedition",
        "Adj. EV": 0.11817883679254382,
        "Pack Value": 1199.99,
        "EV": 141.81342236268466,
        "Last Updated": "2025-10-03 15:11:34",
        "SetNumber": 201
    },
    {
        "Set Name": "Aquapolis",
        "Adj. EV": 0.15052135821360116,
        "Pack Value": 1050.99,
        "EV": 158.19644226891268,
        "Last Updated": "2025-10-03 15:11:34",
        "SetNumber": 202
    },
    {
        "Set Name": "Skyridge",
        "Adj. EV": 0.15810576694891698,
        "Pack Value": 1799.99,
        "EV": 284.5887994503811,
        "Last Updated": "2025-10-03 15:11:34",
        "SetNumber": 203
    },
    {
        "Set Name": "Ruby and Sapphire",
        "Adj. EV": 0.477929775060816,
        "Pack Value": 59.99,
        "EV": 28.671007205898356,
        "Last Updated": "2025-10-03 15:11:34",
        "SetNumber": 300
    },
    {
        "Set Name": "Sandstorm",
        "Adj. EV": 0.07852398108152078,
        "Pack Value": 496.95,
        "EV": 39.02249239846175,
        "Last Updated": "2025-10-03 15:11:34",
        "SetNumber": 301
    },
    {
        "Set Name": "Dragon",
        "Adj. EV": 0.04554470085099202,
        "Pack Value": 1047.5,
        "EV": 47.708074141414144,
        "Last Updated": "2025-10-03 15:11:34",
        "SetNumber": 302
    },
    {
        "Set Name": "Team Magma vs Team Aqua",
        "Adj. EV": 0.1761672804834055,
        "Pack Value": 300.0,
        "EV": 52.85018414502165,
        "Last Updated": "2025-10-03 15:11:34",
        "SetNumber": 303
    },
    {
        "Set Name": "Hidden Legends",
        "Adj. EV": 0.11788140262186111,
        "Pack Value": 319.94,
        "EV": 37.714975954838245,
        "Last Updated": "2025-10-03 15:11:34",
        "SetNumber": 304
    },
    {
        "Set Name": "FireRed & LeafGreen",
        "Adj. EV": 0.09230542189368074,
        "Pack Value": 622.48,
        "EV": 57.45827902037839,
        "Last Updated": "2025-10-03 15:11:34",
        "SetNumber": 305
    },
    {
        "Set Name": "Emerald",
        "Adj. EV": 0.123197736544264,
        "Pack Value": 424.5,
        "EV": 52.29743916304007,
        "Last Updated": "2025-10-03 15:11:34",
        "SetNumber": 306
    },
    {
        "Set Name": "Team Rocket Returns",
        "Adj. EV": 0.06501964310725326,
        "Pack Value": 1999.99,
        "EV": 130.03863601807547,
        "Last Updated": "2025-10-03 15:11:34",
        "SetNumber": 400
    },
    {
        "Set Name": "Deoxys",
        "Adj. EV": 0.029813157290163022,
        "Pack Value": 1599.99,
        "EV": 47.70075353268793,
        "Last Updated": "2025-10-03 15:11:34",
        "SetNumber": 401
    },
    {
        "Set Name": "Unseen Forces",
        "Adj. EV": 0.09174285693508434,
        "Pack Value": 699.97,
        "EV": 64.217247568851,
        "Last Updated": "2025-10-03 15:11:34",
        "SetNumber": 402
    },
    {
        "Set Name": "Delta Species",
        "Adj. EV": 0.15522217056034096,
        "Pack Value": 749.975,
        "EV": 116.41274736599172,
        "Last Updated": "2025-10-03 15:11:34",
        "SetNumber": 403
    },
    {
        "Set Name": "Legend Maker",
        "Adj. EV": 0.097125308962804,
        "Pack Value": 481.995,
        "EV": 46.81391329352671,
        "Last Updated": "2025-10-03 15:11:34",
        "SetNumber": 404
    },
    {
        "Set Name": "Holon Phantoms",
        "Adj. EV": 0.10198854014658598,
        "Pack Value": 699.95,
        "EV": 71.38687867560286,
        "Last Updated": "2025-10-03 15:11:34",
        "SetNumber": 405
    },
    {
        "Set Name": "Crystal Guardians",
        "Adj. EV": 0.10464468870918396,
        "Pack Value": 499.99,
        "EV": 52.32129790770489,
        "Last Updated": "2025-10-03 15:11:34",
        "SetNumber": 406
    },
    {
        "Set Name": "Dragon Frontiers",
        "Adj. EV": 0.06523696734585688,
        "Pack Value": 899.95,
        "EV": 58.7100087629039,
        "Last Updated": "2025-10-03 15:11:34",
        "SetNumber": 407
    },
    {
        "Set Name": "Power Keepers",
        "Adj. EV": 0.058213297632967176,
        "Pack Value": 662.0,
        "EV": 38.53720303302427,
        "Last Updated": "2025-10-03 15:11:34",
        "SetNumber": 408
    },
    {
        "Set Name": "Diamond and Pearl",
        "Adj. EV": 0.1385485989687606,
        "Pack Value": 154.75,
        "EV": 21.440395690415702,
        "Last Updated": "2025-10-03 15:11:34",
        "SetNumber": 500
    },
    {
        "Set Name": "Mysterious Treasures",
        "Adj. EV": 0.12996234763136377,
        "Pack Value": 126.3,
        "EV": 16.414244505841243,
        "Last Updated": "2025-10-03 15:11:34",
        "SetNumber": 501
    },
    {
        "Set Name": "Secret Wonders",
        "Adj. EV": 0.07711305946512,
        "Pack Value": 299.0,
        "EV": 23.05680478007088,
        "Last Updated": "2025-10-03 15:11:34",
        "SetNumber": 502
    },
    {
        "Set Name": "Great Encounters",
        "Adj. EV": 0.09047343711210348,
        "Pack Value": 211.99,
        "EV": 19.179463933394818,
        "Last Updated": "2025-10-03 15:11:34",
        "SetNumber": 503
    },
    {
        "Set Name": "Majestic Dawn",
        "Adj. EV": 0.0784239860670194,
        "Pack Value": 450.0,
        "EV": 35.29079373015873,
        "Last Updated": "2025-10-03 15:11:34",
        "SetNumber": 504
    },
    {
        "Set Name": "Legends Awakened",
        "Adj. EV": 0.11210595205059995,
        "Pack Value": 245.0,
        "EV": 27.465958252396987,
        "Last Updated": "2025-10-03 15:11:34",
        "SetNumber": 505
    },
    {
        "Set Name": "Stormfront",
        "Adj. EV": 0.08358370303028821,
        "Pack Value": 299.99,
        "EV": 25.07427507205616,
        "Last Updated": "2025-10-03 15:11:34",
        "SetNumber": 506
    },
    {
        "Set Name": "Platinum",
        "Adj. EV": 0.1288790684089557,
        "Pack Value": 169.99,
        "EV": 21.90815283883838,
        "Last Updated": "2025-10-03 15:11:34",
        "SetNumber": 507
    },
    {
        "Set Name": "Rising Rivals",
        "Adj. EV": 0.1047519890788224,
        "Pack Value": 300.0,
        "EV": 31.42559672364672,
        "Last Updated": "2025-10-03 15:11:34",
        "SetNumber": 508
    },
    {
        "Set Name": "Supreme Victors",
        "Adj. EV": 0.1078942657730058,
        "Pack Value": 319.75,
        "EV": 34.499191480918604,
        "Last Updated": "2025-10-03 15:11:34",
        "SetNumber": 509
    },
    {
        "Set Name": "Arceus",
        "Adj. EV": 0.12168553685746876,
        "Pack Value": 232.49,
        "EV": 28.290670463992914,
        "Last Updated": "2025-10-03 15:11:34",
        "SetNumber": 510
    },
    {
        "Set Name": "HeartGold SoulSilver",
        "Adj. EV": 0.2028321872614572,
        "Pack Value": 325.0,
        "EV": 65.92046085997359,
        "Last Updated": "2025-10-03 15:11:34",
        "SetNumber": 600
    },
    {
        "Set Name": "Unleashed",
        "Adj. EV": 0.1533662557940692,
        "Pack Value": 174.99,
        "EV": 26.837561101404173,
        "Last Updated": "2025-10-03 15:11:34",
        "SetNumber": 601
    },
    {
        "Set Name": "Undaunted",
        "Adj. EV": 0.20327070371024977,
        "Pack Value": 201.51,
        "EV": 40.96107950465243,
        "Last Updated": "2025-10-03 15:11:34",
        "SetNumber": 602
    },
    {
        "Set Name": "Triumphant",
        "Adj. EV": 0.22442580522248243,
        "Pack Value": 130.0,
        "EV": 29.175354678922716,
        "Last Updated": "2025-10-03 15:11:34",
        "SetNumber": 603
    },
    {
        "Set Name": "Call of Legends",
        "Adj. EV": 0.18953760410294904,
        "Pack Value": 375.0,
        "EV": 71.07660153860589,
        "Last Updated": "2025-10-03 15:11:34",
        "SetNumber": 604
    },
    {
        "Set Name": "Black and White",
        "Adj. EV": 0.15857877610944043,
        "Pack Value": 87.73,
        "EV": 13.91211602808121,
        "Last Updated": "2025-10-03 15:11:34",
        "SetNumber": 700
    },
    {
        "Set Name": "Emerging Powers",
        "Adj. EV": 0.07161925694199625,
        "Pack Value": 78.13,
        "EV": 5.595612544878167,
        "Last Updated": "2025-10-03 15:11:34",
        "SetNumber": 701
    },
    {
        "Set Name": "Noble Victories",
        "Adj. EV": 0.14614146106497947,
        "Pack Value": 105.95,
        "EV": 15.483687799834573,
        "Last Updated": "2025-10-03 15:11:34",
        "SetNumber": 702
    },
    {
        "Set Name": "Next Destinies",
        "Adj. EV": 0.10341188967061929,
        "Pack Value": 121.09,
        "EV": 12.52214572021529,
        "Last Updated": "2025-10-03 15:11:34",
        "SetNumber": 703
    },
    {
        "Set Name": "Dark Explorers",
        "Adj. EV": 0.07835848574327835,
        "Pack Value": 350.0,
        "EV": 27.42547001014742,
        "Last Updated": "2025-10-03 15:11:34",
        "SetNumber": 704
    },
    {
        "Set Name": "Dragons Exalted",
        "Adj. EV": 0.11026165145569573,
        "Pack Value": 167.99,
        "EV": 18.522854828042327,
        "Last Updated": "2025-10-03 15:11:34",
        "SetNumber": 705
    },
    {
        "Set Name": "Boundaries Crossed",
        "Adj. EV": 0.12072486088601818,
        "Pack Value": 135.5,
        "EV": 16.358218650055463,
        "Last Updated": "2025-10-03 15:11:34",
        "SetNumber": 706
    },
    {
        "Set Name": "Plasma Storm",
        "Adj. EV": 0.07138078408168211,
        "Pack Value": 290.31,
        "EV": 20.722555426753132,
        "Last Updated": "2025-10-03 15:11:34",
        "SetNumber": 707
    },
    {
        "Set Name": "Plasma Freeze",
        "Adj. EV": 0.12283563189720331,
        "Pack Value": 175.0,
        "EV": 21.49623558201058,
        "Last Updated": "2025-10-03 15:11:34",
        "SetNumber": 708
    },
    {
        "Set Name": "Plasma Blast",
        "Adj. EV": 0.12718236469284275,
        "Pack Value": 96.42,
        "EV": 12.262923603683898,
        "Last Updated": "2025-10-03 15:11:34",
        "SetNumber": 709
    },
    {
        "Set Name": "Legendary Treasures",
        "Adj. EV": 0.2617343567991428,
        "Pack Value": 165.95,
        "EV": 43.43481651081775,
        "Last Updated": "2025-10-03 15:11:34",
        "SetNumber": 710
    },
    {
        "Set Name": "XY Base Set",
        "Adj. EV": 0.13947597612752183,
        "Pack Value": 53.28,
        "EV": 7.431280008074363,
        "Last Updated": "2025-10-03 15:11:34",
        "SetNumber": 800
    },
    {
        "Set Name": "XY - Flashfire",
        "Adj. EV": 0.1234959715530435,
        "Pack Value": 120.25,
        "EV": 14.85039057925348,
        "Last Updated": "2025-10-03 15:11:34",
        "SetNumber": 801
    },
    {
        "Set Name": "XY - Furious Fists",
        "Adj. EV": 0.21742794798359005,
        "Pack Value": 50.29,
        "EV": 10.934451504094744,
        "Last Updated": "2025-10-03 15:11:34",
        "SetNumber": 802
    },
    {
        "Set Name": "XY - Phantom Forces",
        "Adj. EV": 0.16860536826899483,
        "Pack Value": 117.36,
        "EV": 19.787526020049235,
        "Last Updated": "2025-10-03 15:11:34",
        "SetNumber": 803
    },
    {
        "Set Name": "XY - Primal Clash",
        "Adj. EV": 0.21320489996254424,
        "Pack Value": 46.44,
        "EV": 9.901235554260554,
        "Last Updated": "2025-10-03 15:11:34",
        "SetNumber": 804
    },
    {
        "Set Name": "XY - Roaring Skies",
        "Adj. EV": 0.19434984917857093,
        "Pack Value": 54.06,
        "EV": 10.506552846593545,
        "Last Updated": "2025-10-03 15:11:34",
        "SetNumber": 805
    },
    {
        "Set Name": "XY - Ancient Origins",
        "Adj. EV": 0.21761711433929687,
        "Pack Value": 85.3,
        "EV": 18.562739853142023,
        "Last Updated": "2025-10-03 15:11:34",
        "SetNumber": 806
    },
    {
        "Set Name": "XY - BREAKthrough",
        "Adj. EV": 0.4494789502036785,
        "Pack Value": 33.22,
        "EV": 14.931690725766199,
        "Last Updated": "2025-10-03 15:11:34",
        "SetNumber": 807
    },
    {
        "Set Name": "XY - BREAKpoint",
        "Adj. EV": 0.4354028383598969,
        "Pack Value": 30.23,
        "EV": 13.162227803619684,
        "Last Updated": "2025-10-03 15:11:34",
        "SetNumber": 808
    },
    {
        "Set Name": "XY - Fates Collide",
        "Adj. EV": 0.2875789560338969,
        "Pack Value": 35.06,
        "EV": 10.082518198548426,
        "Last Updated": "2025-10-03 15:11:34",
        "SetNumber": 809
    },
    {
        "Set Name": "XY - Steam Siege",
        "Adj. EV": 0.30425277083319424,
        "Pack Value": 19.85,
        "EV": 6.039417501038907,
        "Last Updated": "2025-10-03 15:11:34",
        "SetNumber": 810
    },
    {
        "Set Name": "XY - Evolutions",
        "Adj. EV": 0.3072510773118022,
        "Pack Value": 44.19,
        "EV": 13.577425106408539,
        "Last Updated": "2025-10-03 15:11:34",
        "SetNumber": 811
    },
    {
        "Set Name": "SM Base Set",
        "Adj. EV": 0.22036354835121766,
        "Pack Value": 14.46,
        "EV": 3.1864569091586077,
        "Last Updated": "2025-10-03 15:11:34",
        "SetNumber": 900
    },
    {
        "Set Name": "SM - Guardians Rising",
        "Adj. EV": 0.1485547897693363,
        "Pack Value": 23.87,
        "EV": 3.5460028317940577,
        "Last Updated": "2025-10-03 15:11:34",
        "SetNumber": 901
    },
    {
        "Set Name": "SM - Burning Shadows",
        "Adj. EV": 0.1777475966181253,
        "Pack Value": 22.94,
        "EV": 4.077529866419795,
        "Last Updated": "2025-10-03 15:11:34",
        "SetNumber": 902
    },
    {
        "Set Name": "SM - Crimson Invasion",
        "Adj. EV": 0.26699298466936994,
        "Pack Value": 13.42,
        "EV": 3.583045854262944,
        "Last Updated": "2025-10-03 15:11:34",
        "SetNumber": 903
    },
    {
        "Set Name": "SM - Ultra Prism",
        "Adj. EV": 0.23191326945937193,
        "Pack Value": 36.12,
        "EV": 8.376707292872513,
        "Last Updated": "2025-10-03 15:11:34",
        "SetNumber": 904
    },
    {
        "Set Name": "SM - Forbidden Light",
        "Adj. EV": 0.3151468954459103,
        "Pack Value": 22.99,
        "EV": 7.245227126301478,
        "Last Updated": "2025-10-03 15:11:34",
        "SetNumber": 905
    },
    {
        "Set Name": "SM - Celestial Storm",
        "Adj. EV": 0.16069082670630636,
        "Pack Value": 43.57,
        "EV": 7.001299319593768,
        "Last Updated": "2025-10-03 15:11:34",
        "SetNumber": 906
    },
    {
        "Set Name": "SM - Lost Thunder",
        "Adj. EV": 0.27089936426036326,
        "Pack Value": 29.1,
        "EV": 7.883171499976572,
        "Last Updated": "2025-10-03 15:11:34",
        "SetNumber": 907
    },
    {
        "Set Name": "SM - Team Up",
        "Adj. EV": 0.11750624091560008,
        "Pack Value": 179.59,
        "EV": 21.10294580603262,
        "Last Updated": "2025-10-03 15:11:34",
        "SetNumber": 908
    },
    {
        "Set Name": "SM - Unbroken Bonds",
        "Adj. EV": 0.19870333655609063,
        "Pack Value": 51.54,
        "EV": 10.24116996610091,
        "Last Updated": "2025-10-03 15:11:34",
        "SetNumber": 909
    },
    {
        "Set Name": "SM - Unified Minds",
        "Adj. EV": 0.1869812307801225,
        "Pack Value": 59.29,
        "EV": 11.086117172953463,
        "Last Updated": "2025-10-03 15:11:34",
        "SetNumber": 910
    },
    {
        "Set Name": "SM - Cosmic Eclipse",
        "Adj. EV": 0.23905725434341865,
        "Pack Value": 66.13,
        "EV": 15.808856229730274,
        "Last Updated": "2025-10-03 15:11:34",
        "SetNumber": 911
    },
    {
        "Set Name": "SWSH01: Sword & Shield Base Set",
        "Adj. EV": 0.3223455930364299,
        "Pack Value": 8.36,
        "EV": 2.6948091577845537,
        "Last Updated": "2025-10-03 15:11:34",
        "SetNumber": 1000
    },
    {
        "Set Name": "SWSH02: Rebel Clash",
        "Adj. EV": 0.31580329820988834,
        "Pack Value": 7.57,
        "EV": 2.3906309674488546,
        "Last Updated": "2025-10-03 15:11:34",
        "SetNumber": 1001
    },
    {
        "Set Name": "SWSH03: Darkness Ablaze",
        "Adj. EV": 0.30138465239907825,
        "Pack Value": 6.78,
        "EV": 2.0433879432657505,
        "Last Updated": "2025-10-03 15:11:34",
        "SetNumber": 1002
    },
    {
        "Set Name": "SWSH04: Vivid Voltage",
        "Adj. EV": 0.38840351314509525,
        "Pack Value": 6.68,
        "EV": 2.5945354678092363,
        "Last Updated": "2025-10-03 15:11:34",
        "SetNumber": 1003
    },
    {
        "Set Name": "SWSH05: Battle Styles",
        "Adj. EV": 0.2952364063425784,
        "Pack Value": 6.81,
        "EV": 2.010559927192959,
        "Last Updated": "2025-10-03 15:11:34",
        "SetNumber": 1004
    },
    {
        "Set Name": "SWSH06: Chilling Reign",
        "Adj. EV": 0.26804478100779777,
        "Pack Value": 8.77,
        "EV": 2.3507527294383865,
        "Last Updated": "2025-10-03 15:11:34",
        "SetNumber": 1005
    },
    {
        "Set Name": "SWSH07: Evolving Skies",
        "Adj. EV": 0.2537706422610517,
        "Pack Value": 30.66,
        "EV": 7.780607891723847,
        "Last Updated": "2025-10-03 15:11:34",
        "SetNumber": 1006
    },
    {
        "Set Name": "SWSH08: Fusion Strike",
        "Adj. EV": 0.26195935858362884,
        "Pack Value": 12.82,
        "EV": 3.3583189770421216,
        "Last Updated": "2025-10-03 15:11:34",
        "SetNumber": 1007
    },
    {
        "Set Name": "SWSH09: Brilliant Stars",
        "Adj. EV": 0.6704916991805994,
        "Pack Value": 8.62,
        "EV": 5.779638446936766,
        "Last Updated": "2025-10-03 15:11:34",
        "SetNumber": 1100
    },
    {
        "Set Name": "SWSH10: Astral Radiance",
        "Adj. EV": 0.49131094856351015,
        "Pack Value": 7.16,
        "EV": 3.5177863917147327,
        "Last Updated": "2025-10-03 15:11:34",
        "SetNumber": 1101
    },
    {
        "Set Name": "SWSH11: Lost Origin",
        "Adj. EV": 0.40049135431121735,
        "Pack Value": 11.04,
        "EV": 4.421424551595839,
        "Last Updated": "2025-10-03 15:11:34",
        "SetNumber": 1102
    },
    {
        "Set Name": "SWSH12: Silver Tempest",
        "Adj. EV": 0.4962895259566107,
        "Pack Value": 7.66,
        "EV": 3.801577768827638,
        "Last Updated": "2025-10-03 15:11:34",
        "SetNumber": 1103
    },
    {
        "Set Name": "SV01: Scarlet & Violet Base Set",
        "Adj. EV": 0.4453065321707863,
        "Pack Value": 6.6,
        "EV": 2.9390231123271895,
        "Last Updated": "2025-10-03 15:11:34",
        "SetNumber": 1200
    },
    {
        "Set Name": "SV02: Paldea Evolved",
        "Adj. EV": 0.46243216913657686,
        "Pack Value": 8.99,
        "EV": 4.157265200537826,
        "Last Updated": "2025-10-03 15:11:34",
        "SetNumber": 1201
    },
    {
        "Set Name": "SV03: Obsidian Flames",
        "Adj. EV": 0.4246045999933015,
        "Pack Value": 7.72,
        "EV": 3.2779475119482875,
        "Last Updated": "2025-10-03 15:11:34",
        "SetNumber": 1202
    },
    {
        "Set Name": "SV04: Paradox Rift",
        "Adj. EV": 0.4852441890207261,
        "Pack Value": 6.16,
        "EV": 2.9891042043676728,
        "Last Updated": "2025-10-03 15:11:34",
        "SetNumber": 1203
    },
    {
        "Set Name": "SV05: Temporal Forces",
        "Adj. EV": 0.4872897037930239,
        "Pack Value": 6.18,
        "EV": 3.0114503694408876,
        "Last Updated": "2025-10-03 15:11:34",
        "SetNumber": 1204
    },
    {
        "Set Name": "SV06: Twilight Masquerade",
        "Adj. EV": 0.4915644193877979,
        "Pack Value": 6.86,
        "EV": 3.3721319170002935,
        "Last Updated": "2025-10-03 15:11:34",
        "SetNumber": 1205
    },
    {
        "Set Name": "SV07: Stellar Crown",
        "Adj. EV": 0.41565628957980366,
        "Pack Value": 6.94,
        "EV": 2.8846546496838377,
        "Last Updated": "2025-10-03 15:11:34",
        "SetNumber": 1206
    },
    {
        "Set Name": "SV08: Surging Sparks",
        "Adj. EV": 0.44458204880213864,
        "Pack Value": 7.06,
        "EV": 3.1387492645430988,
        "Last Updated": "2025-10-03 15:11:34",
        "SetNumber": 1207
    },
    {
        "Set Name": "SV09: Journey Together",
        "Adj. EV": 0.4723789827190078,
        "Pack Value": 6.83,
        "EV": 3.226348451970823,
        "Last Updated": "2025-10-03 15:11:34",
        "SetNumber": 1208
    },
    {
        "Set Name": "SV10: Destined Rivals",
        "Adj. EV": 0.5522039587875323,
        "Pack Value": 9.4,
        "EV": 5.190717212602803,
        "Last Updated": "2025-10-03 15:11:34",
        "SetNumber": 1209
    },
    {
        "Set Name": "Dragon Vault",
        "Adj. EV": 0.1344623231161558,
        "Pack Value": 199.99,
        "EV": 26.89112,
        "Last Updated": "2025-10-03 15:11:34",
        "SetNumber": 705.5
    },
    {
        "Set Name": "Double Crisis",
        "Adj. EV": 0.2928475038550415,
        "Pack Value": 236.48,
        "EV": 69.25257771164021,
        "Last Updated": "2025-10-03 15:11:34",
        "SetNumber": 804.5
    },
    {
        "Set Name": "Shining Legends",
        "Adj. EV": 0.1933514544976323,
        "Pack Value": 61.69,
        "EV": 11.927851227958936,
        "Last Updated": "2025-10-03 15:11:34",
        "SetNumber": 902.5
    },
    {
        "Set Name": "Dragon Majesty",
        "Adj. EV": 0.19982369650310683,
        "Pack Value": 53.06,
        "EV": 10.602645336454849,
        "Last Updated": "2025-10-03 15:11:34",
        "SetNumber": 906.5
    },
    {
        "Set Name": "Champions Path",
        "Adj. EV": 0.2383692577778319,
        "Pack Value": 14.41,
        "EV": 3.434901004578558,
        "Last Updated": "2025-10-03 15:11:34",
        "SetNumber": 1002.5
    },
    {
        "Set Name": "Pokemon Go",
        "Adj. EV": 0.4581235787182167,
        "Pack Value": 8.7,
        "EV": 3.985675134848485,
        "Last Updated": "2025-10-03 15:11:34",
        "SetNumber": 1101.5
    },
    {
        "Set Name": "Pokemon 151",
        "Adj. EV": 0.45219079486457187,
        "Pack Value": 18.28,
        "EV": 8.266047730124374,
        "Last Updated": "2025-10-03 15:11:34",
        "SetNumber": 1202.5
    },
    {
        "Set Name": "Paldean Fates",
        "Adj. EV": 0.3999783323119907,
        "Pack Value": 13.66,
        "EV": 5.463704019381793,
        "Last Updated": "2025-10-03 15:11:34",
        "SetNumber": 1203.5
    },
    {
        "Set Name": "Shrouded Fable",
        "Adj. EV": 0.5979635156001207,
        "Pack Value": 7.67,
        "EV": 4.586380164652926,
        "Last Updated": "2025-10-03 15:11:34",
        "SetNumber": 1205.5
    },
    {
        "Set Name": "Hidden Fates",
        "Adj. EV": 0.3675437484438142,
        "Pack Value": 35.1,
        "EV": 12.900785570377879,
        "Last Updated": "2025-10-03 15:11:34",
        "SetNumber": 910.5
    },
    {
        "Set Name": "Shining Fates",
        "Adj. EV": 0.2540690361895869,
        "Pack Value": 11.91,
        "EV": 3.0259622210179806,
        "Last Updated": "2025-10-03 15:11:34",
        "SetNumber": 1003.5
    },
    {
        "Set Name": "Generations",
        "Adj. EV": 0.2506032651849159,
        "Pack Value": 192.61,
        "EV": 48.26869490726665,
        "Last Updated": "2025-10-03 15:11:34",
        "SetNumber": 808.5
    },
    {
        "Set Name": "Crown Zenith",
        "Adj. EV": 0.5793413400366997,
        "Pack Value": 13.35,
        "EV": 7.73420688948994,
        "Last Updated": "2025-10-03 15:11:34",
        "SetNumber": 1103.5
    },
    {
        "Set Name": "Celebrations",
        "Adj. EV": 0.5079056120958143,
        "Pack Value": 18.38,
        "EV": 9.335305150321066,
        "Last Updated": "2025-10-03 15:11:34",
        "SetNumber": 1006.5
    },
    {
        "Set Name": "Prismatic Evolutions",
        "Adj. EV": 0.5949247456649379,
        "Pack Value": 7.83,
        "EV": 4.658260758556464,
        "Last Updated": "2025-10-03 15:11:34",
        "SetNumber": 1207.5
    }
]